{
	"speed": 1.2,
	"spectator": "gf",
	"mustHitSections": [
		false,
		false,
		true,
		true,
		false,
		false,
		true,
		true,
		false,
		false,
		true,
		true,
		false,
		false,
		true,
		true,
		false,
		false,
		true,
		true,
		false,
		false,
		true,
		true,
		false,
		false,
		true,
		true,
		false,
		false,
		true,
		true,
		false,
		false,
		true,
		true,
		false,
		false,
		true,
		true,
		false,
		false,
		true,
		true,
		true,
		true
	],
	"opponent": "senpai-angry",
	"bpm": 120,
	"player": "bf-pixel",
	"sectionList": [
		{
			"length": 16,
			"notes": [
				{
					"strumTime": 500,
					"sustain": 0,
					"direction": 3,
					"noteAnim": "singRIGHT",
					"noteType": "",
					"mustPress": false
				},
				{
					"strumTime": 1000,
					"sustain": 250,
					"direction": 0,
					"noteAnim": "singLEFT",
					"noteType": "",
					"mustPress": false
				},
				{
					"strumTime": 1375,
					"sustain": 0,
					"direction": 1,
					"noteAnim": "singDOWN",
					"noteType": "",
					"mustPress": false
				},
				{
					"strumTime": 1875,
					"sustain": 0,
					"direction": 2,
					"noteAnim": "singUP",
					"noteType": "",
					"mustPress": false
				}
			]
		},
		{
			"length": 16,
			"notes": [
				{
					"strumTime": 2375,
					"sustain": 0,
					"direction": 2,
					"noteAnim": "singUP",
					"noteType": "",
					"mustPress": false
				},
				{
					"strumTime": 3000,
					"sustain": 250,
					"direction": 3,
					"noteAnim": "singRIGHT",
					"noteType": "",
					"mustPress": false
				},
				{
					"strumTime": 3375,
					"sustain": 0,
					"direction": 3,
					"noteAnim": "singRIGHT",
					"noteType": "",
					"mustPress": false
				},
				{
					"strumTime": 3625,
					"sustain": 0,
					"direction": 0,
					"noteAnim": "singLEFT",
					"noteType": "",
					"mustPress": false
				}
			]
		},
		{
			"length": 16,
			"notes": [
				{
					"strumTime": 4500,
					"sustain": 0,
					"direction": 3,
					"noteAnim": "singRIGHT",
					"noteType": "",
					"mustPress": true
				},
				{
					"strumTime": 5000,
					"sustain": 250,
					"direction": 0,
					"noteAnim": "singLEFT",
					"noteType": "",
					"mustPress": true
				},
				{
					"strumTime": 5375,
					"sustain": 0,
					"direction": 1,
					"noteAnim": "singDOWN",
					"noteType": "",
					"mustPress": true
				},
				{
					"strumTime": 5875,
					"sustain": 0,
					"direction": 2,
					"noteAnim": "singUP",
					"noteType": "",
					"mustPress": true
				}
			]
		},
		{
			"length": 16,
			"notes": [
				{
					"strumTime": 6375,
					"sustain": 0,
					"direction": 2,
					"noteAnim": "singUP",
					"noteType": "",
					"mustPress": true
				},
				{
					"strumTime": 7000,
					"sustain": 250,
					"direction": 3,
					"noteAnim": "singRIGHT",
					"noteType": "",
					"mustPress": true
				},
				{
					"strumTime": 7375,
					"sustain": 0,
					"direction": 3,
					"noteAnim": "singRIGHT",
					"noteType": "",
					"mustPress": true
				},
				{
					"strumTime": 7625,
					"sustain": 0,
					"direction": 0,
					"noteAnim": "singLEFT",
					"noteType": "",
					"mustPress": true
				}
			]
		},
		{
			"length": 16,
			"notes": [
				{
					"strumTime": 8000,
					"sustain": 125,
					"direction": 2,
					"noteAnim": "singUP",
					"noteType": "",
					"mustPress": false
				},
				{
					"strumTime": 8500,
					"sustain": 0,
					"direction": 2,
					"noteAnim": "singUP",
					"noteType": "",
					"mustPress": false
				},
				{
					"strumTime": 8875,
					"sustain": 250,
					"direction": 3,
					"noteAnim": "singRIGHT",
					"noteType": "",
					"mustPress": false
				},
				{
					"strumTime": 9500,
					"sustain": 0,
					"direction": 0,
					"noteAnim": "singLEFT",
					"noteType": "",
					"mustPress": false
				},
				{
					"strumTime": 9875,
					"sustain": 250,
					"direction": 3,
					"noteAnim": "singRIGHT",
					"noteType": "",
					"mustPress": false
				}
			]
		},
		{
			"length": 16,
			"notes": [
				{
					"strumTime": 10250,
					"sustain": 0,
					"direction": 1,
					"noteAnim": "singDOWN",
					"noteType": "",
					"mustPress": false
				},
				{
					"strumTime": 10500,
					"sustain": 0,
					"direction": 3,
					"noteAnim": "singRIGHT",
					"noteType": "",
					"mustPress": false
				},
				{
					"strumTime": 10875,
					"sustain": 250,
					"direction": 3,
					"noteAnim": "singRIGHT",
					"noteType": "",
					"mustPress": false
				},
				{
					"strumTime": 11250,
					"sustain": 0,
					"direction": 1,
					"noteAnim": "singDOWN",
					"noteType": "",
					"mustPress": false
				},
				{
					"strumTime": 11500,
					"sustain": 0,
					"direction": 0,
					"noteAnim": "singLEFT",
					"noteType": "",
					"mustPress": false
				},
				{
					"strumTime": 11750,
					"sustain": 0,
					"direction": 3,
					"noteAnim": "singRIGHT",
					"noteType": "",
					"mustPress": false
				}
			]
		},
		{
			"length": 16,
			"notes": [
				{
					"strumTime": 12000,
					"sustain": 125,
					"direction": 2,
					"noteAnim": "singUP",
					"noteType": "",
					"mustPress": true
				},
				{
					"strumTime": 12500,
					"sustain": 0,
					"direction": 2,
					"noteAnim": "singUP",
					"noteType": "",
					"mustPress": true
				},
				{
					"strumTime": 12875,
					"sustain": 250,
					"direction": 3,
					"noteAnim": "singRIGHT",
					"noteType": "",
					"mustPress": true
				},
				{
					"strumTime": 13500,
					"sustain": 0,
					"direction": 0,
					"noteAnim": "singLEFT",
					"noteType": "",
					"mustPress": true
				},
				{
					"strumTime": 13875,
					"sustain": 250,
					"direction": 3,
					"noteAnim": "singRIGHT",
					"noteType": "",
					"mustPress": true
				}
			]
		},
		{
			"length": 16,
			"notes": [
				{
					"strumTime": 14250,
					"sustain": 0,
					"direction": 1,
					"noteAnim": "singDOWN",
					"noteType": "",
					"mustPress": true
				},
				{
					"strumTime": 14500,
					"sustain": 0,
					"direction": 3,
					"noteAnim": "singRIGHT",
					"noteType": "",
					"mustPress": true
				},
				{
					"strumTime": 14875,
					"sustain": 250,
					"direction": 3,
					"noteAnim": "singRIGHT",
					"noteType": "",
					"mustPress": true
				},
				{
					"strumTime": 15250,
					"sustain": 0,
					"direction": 1,
					"noteAnim": "singDOWN",
					"noteType": "",
					"mustPress": true
				},
				{
					"strumTime": 15500,
					"sustain": 0,
					"direction": 0,
					"noteAnim": "singLEFT",
					"noteType": "",
					"mustPress": true
				},
				{
					"strumTime": 15750,
					"sustain": 0,
					"direction": 3,
					"noteAnim": "singRIGHT",
					"noteType": "",
					"mustPress": true
				}
			]
		},
		{
			"length": 16,
			"notes": [
				{
					"strumTime": 16500,
					"sustain": 0,
					"direction": 0,
					"noteAnim": "singLEFT",
					"noteType": "",
					"mustPress": false
				},
				{
					"strumTime": 17000,
					"sustain": 125,
					"direction": 3,
					"noteAnim": "singRIGHT",
					"noteType": "",
					"mustPress": false
				},
				{
					"strumTime": 17250,
					"sustain": 0,
					"direction": 1,
					"noteAnim": "singDOWN",
					"noteType": "",
					"mustPress": false
				},
				{
					"strumTime": 17500,
					"sustain": 0,
					"direction": 0,
					"noteAnim": "singLEFT",
					"noteType": "",
					"mustPress": false
				}
			]
		},
		{
			"length": 16,
			"notes": [
				{
					"strumTime": 18000,
					"sustain": 0,
					"direction": 0,
					"noteAnim": "singLEFT",
					"noteType": "",
					"mustPress": false
				},
				{
					"strumTime": 18250,
					"sustain": 0,
					"direction": 3,
					"noteAnim": "singRIGHT",
					"noteType": "",
					"mustPress": false
				},
				{
					"strumTime": 18500,
					"sustain": 0,
					"direction": 0,
					"noteAnim": "singLEFT",
					"noteType": "",
					"mustPress": false
				},
				{
					"strumTime": 19000,
					"sustain": 0,
					"direction": 3,
					"noteAnim": "singRIGHT",
					"noteType": "",
					"mustPress": false
				},
				{
					"strumTime": 19250,
					"sustain": 0,
					"direction": 1,
					"noteAnim": "singDOWN",
					"noteType": "",
					"mustPress": false
				},
				{
					"strumTime": 19500,
					"sustain": 0,
					"direction": 0,
					"noteAnim": "singLEFT",
					"noteType": "",
					"mustPress": false
				},
				{
					"strumTime": 19750,
					"sustain": 0,
					"direction": 3,
					"noteAnim": "singRIGHT",
					"noteType": "",
					"mustPress": false
				}
			]
		},
		{
			"length": 16,
			"notes": [
				{
					"strumTime": 20500,
					"sustain": 0,
					"direction": 0,
					"noteAnim": "singLEFT",
					"noteType": "",
					"mustPress": true
				},
				{
					"strumTime": 21000,
					"sustain": 125,
					"direction": 3,
					"noteAnim": "singRIGHT",
					"noteType": "",
					"mustPress": true
				},
				{
					"strumTime": 21250,
					"sustain": 0,
					"direction": 1,
					"noteAnim": "singDOWN",
					"noteType": "",
					"mustPress": true
				},
				{
					"strumTime": 21500,
					"sustain": 0,
					"direction": 0,
					"noteAnim": "singLEFT",
					"noteType": "",
					"mustPress": true
				}
			]
		},
		{
			"length": 16,
			"notes": [
				{
					"strumTime": 22000,
					"sustain": 0,
					"direction": 0,
					"noteAnim": "singLEFT",
					"noteType": "",
					"mustPress": true
				},
				{
					"strumTime": 22250,
					"sustain": 0,
					"direction": 3,
					"noteAnim": "singRIGHT",
					"noteType": "",
					"mustPress": true
				},
				{
					"strumTime": 22500,
					"sustain": 0,
					"direction": 0,
					"noteAnim": "singLEFT",
					"noteType": "",
					"mustPress": true
				},
				{
					"strumTime": 23000,
					"sustain": 0,
					"direction": 3,
					"noteAnim": "singRIGHT",
					"noteType": "",
					"mustPress": true
				},
				{
					"strumTime": 23250,
					"sustain": 0,
					"direction": 1,
					"noteAnim": "singDOWN",
					"noteType": "",
					"mustPress": true
				},
				{
					"strumTime": 23500,
					"sustain": 0,
					"direction": 0,
					"noteAnim": "singLEFT",
					"noteType": "",
					"mustPress": true
				},
				{
					"strumTime": 23750,
					"sustain": 0,
					"direction": 3,
					"noteAnim": "singRIGHT",
					"noteType": "",
					"mustPress": true
				}
			]
		},
		{
			"length": 16,
			"notes": [
				{
					"strumTime": 24000,
					"sustain": 0,
					"direction": 2,
					"noteAnim": "singUP",
					"noteType": "",
					"mustPress": false
				},
				{
					"strumTime": 24625,
					"sustain": 0,
					"direction": 0,
					"noteAnim": "singLEFT",
					"noteType": "",
					"mustPress": false
				},
				{
					"strumTime": 25000,
					"sustain": 0,
					"direction": 3,
					"noteAnim": "singRIGHT",
					"noteType": "",
					"mustPress": false
				},
				{
					"strumTime": 25375,
					"sustain": 0,
					"direction": 3,
					"noteAnim": "singRIGHT",
					"noteType": "",
					"mustPress": false
				},
				{
					"strumTime": 25625,
					"sustain": 0,
					"direction": 0,
					"noteAnim": "singLEFT",
					"noteType": "",
					"mustPress": false
				}
			]
		},
		{
			"length": 16,
			"notes": [
				{
					"strumTime": 26000,
					"sustain": 0,
					"direction": 2,
					"noteAnim": "singUP",
					"noteType": "",
					"mustPress": false
				},
				{
					"strumTime": 26625,
					"sustain": 0,
					"direction": 0,
					"noteAnim": "singLEFT",
					"noteType": "",
					"mustPress": false
				},
				{
					"strumTime": 27000,
					"sustain": 0,
					"direction": 3,
					"noteAnim": "singRIGHT",
					"noteType": "",
					"mustPress": false
				},
				{
					"strumTime": 27375,
					"sustain": 0,
					"direction": 3,
					"noteAnim": "singRIGHT",
					"noteType": "",
					"mustPress": false
				},
				{
					"strumTime": 27625,
					"sustain": 0,
					"direction": 0,
					"noteAnim": "singLEFT",
					"noteType": "",
					"mustPress": false
				}
			]
		},
		{
			"length": 16,
			"notes": [
				{
					"strumTime": 28000,
					"sustain": 0,
					"direction": 2,
					"noteAnim": "singUP",
					"noteType": "",
					"mustPress": true
				},
				{
					"strumTime": 28625,
					"sustain": 0,
					"direction": 0,
					"noteAnim": "singLEFT",
					"noteType": "",
					"mustPress": true
				},
				{
					"strumTime": 29000,
					"sustain": 0,
					"direction": 3,
					"noteAnim": "singRIGHT",
					"noteType": "",
					"mustPress": true
				},
				{
					"strumTime": 29375,
					"sustain": 0,
					"direction": 3,
					"noteAnim": "singRIGHT",
					"noteType": "",
					"mustPress": true
				},
				{
					"strumTime": 29625,
					"sustain": 0,
					"direction": 0,
					"noteAnim": "singLEFT",
					"noteType": "",
					"mustPress": true
				}
			]
		},
		{
			"length": 16,
			"notes": [
				{
					"strumTime": 30000,
					"sustain": 0,
					"direction": 2,
					"noteAnim": "singUP",
					"noteType": "",
					"mustPress": true
				},
				{
					"strumTime": 30625,
					"sustain": 0,
					"direction": 0,
					"noteAnim": "singLEFT",
					"noteType": "",
					"mustPress": true
				},
				{
					"strumTime": 31000,
					"sustain": 0,
					"direction": 3,
					"noteAnim": "singRIGHT",
					"noteType": "",
					"mustPress": true
				},
				{
					"strumTime": 31375,
					"sustain": 0,
					"direction": 3,
					"noteAnim": "singRIGHT",
					"noteType": "",
					"mustPress": true
				},
				{
					"strumTime": 31625,
					"sustain": 0,
					"direction": 0,
					"noteAnim": "singLEFT",
					"noteType": "",
					"mustPress": true
				}
			]
		},
		{
			"length": 16,
			"notes": [
				{
					"strumTime": 32000,
					"sustain": 0,
					"direction": 0,
					"noteAnim": "singLEFT",
					"noteType": "",
					"mustPress": false
				},
				{
					"strumTime": 32500.002,
					"sustain": 0,
					"direction": 3,
					"noteAnim": "singRIGHT",
					"noteType": "",
					"mustPress": false
				},
				{
					"strumTime": 33000,
					"sustain": 0,
					"direction": 2,
					"noteAnim": "singUP",
					"noteType": "",
					"mustPress": false
				},
				{
					"strumTime": 33375,
					"sustain": 0,
					"direction": 3,
					"noteAnim": "singRIGHT",
					"noteType": "",
					"mustPress": false
				},
				{
					"strumTime": 33750,
					"sustain": 0,
					"direction": 0,
					"noteAnim": "singLEFT",
					"noteType": "",
					"mustPress": false
				}
			]
		},
		{
			"length": 16,
			"notes": [
				{
					"strumTime": 34000,
					"sustain": 0,
					"direction": 1,
					"noteAnim": "singDOWN",
					"noteType": "",
					"mustPress": false
				},
				{
					"strumTime": 34500,
					"sustain": 0,
					"direction": 3,
					"noteAnim": "singRIGHT",
					"noteType": "",
					"mustPress": false
				},
				{
					"strumTime": 35000,
					"sustain": 0,
					"direction": 2,
					"noteAnim": "singUP",
					"noteType": "",
					"mustPress": false
				},
				{
					"strumTime": 35375,
					"sustain": 0,
					"direction": 3,
					"noteAnim": "singRIGHT",
					"noteType": "",
					"mustPress": false
				},
				{
					"strumTime": 35750,
					"sustain": 0,
					"direction": 0,
					"noteAnim": "singLEFT",
					"noteType": "",
					"mustPress": false
				}
			]
		},
		{
			"length": 16,
			"notes": [
				{
					"strumTime": 36000,
					"sustain": 0,
					"direction": 0,
					"noteAnim": "singLEFT",
					"noteType": "",
					"mustPress": true
				},
				{
					"strumTime": 36500,
					"sustain": 0,
					"direction": 3,
					"noteAnim": "singRIGHT",
					"noteType": "",
					"mustPress": true
				},
				{
					"strumTime": 37000,
					"sustain": 0,
					"direction": 2,
					"noteAnim": "singUP",
					"noteType": "",
					"mustPress": true
				},
				{
					"strumTime": 37375,
					"sustain": 0,
					"direction": 3,
					"noteAnim": "singRIGHT",
					"noteType": "",
					"mustPress": true
				},
				{
					"strumTime": 37750,
					"sustain": 0,
					"direction": 0,
					"noteAnim": "singLEFT",
					"noteType": "",
					"mustPress": true
				}
			]
		},
		{
			"length": 16,
			"notes": [
				{
					"strumTime": 38000,
					"sustain": 0,
					"direction": 1,
					"noteAnim": "singDOWN",
					"noteType": "",
					"mustPress": true
				},
				{
					"strumTime": 38500,
					"sustain": 0,
					"direction": 3,
					"noteAnim": "singRIGHT",
					"noteType": "",
					"mustPress": true
				},
				{
					"strumTime": 39000,
					"sustain": 0,
					"direction": 2,
					"noteAnim": "singUP",
					"noteType": "",
					"mustPress": true
				},
				{
					"strumTime": 39375,
					"sustain": 0,
					"direction": 3,
					"noteAnim": "singRIGHT",
					"noteType": "",
					"mustPress": true
				},
				{
					"strumTime": 39750,
					"sustain": 0,
					"direction": 0,
					"noteAnim": "singLEFT",
					"noteType": "",
					"mustPress": true
				}
			]
		},
		{
			"length": 16,
			"notes": [
				{
					"strumTime": 40000,
					"sustain": 0,
					"direction": 1,
					"noteAnim": "singDOWN",
					"noteType": "",
					"mustPress": false
				},
				{
					"strumTime": 40500,
					"sustain": 0,
					"direction": 2,
					"noteAnim": "singUP",
					"noteType": "",
					"mustPress": false
				},
				{
					"strumTime": 40750,
					"sustain": 0,
					"direction": 3,
					"noteAnim": "singRIGHT",
					"noteType": "",
					"mustPress": false
				},
				{
					"strumTime": 41000,
					"sustain": 0,
					"direction": 2,
					"noteAnim": "singUP",
					"noteType": "",
					"mustPress": false
				},
				{
					"strumTime": 41375,
					"sustain": 0,
					"direction": 1,
					"noteAnim": "singDOWN",
					"noteType": "",
					"mustPress": false
				},
				{
					"strumTime": 41750,
					"sustain": 0,
					"direction": 3,
					"noteAnim": "singRIGHT",
					"noteType": "",
					"mustPress": false
				}
			]
		},
		{
			"length": 16,
			"notes": [
				{
					"strumTime": 42000,
					"sustain": 0,
					"direction": 1,
					"noteAnim": "singDOWN",
					"noteType": "",
					"mustPress": false
				},
				{
					"strumTime": 42500,
					"sustain": 0,
					"direction": 2,
					"noteAnim": "singUP",
					"noteType": "",
					"mustPress": false
				},
				{
					"strumTime": 42750,
					"sustain": 0,
					"direction": 3,
					"noteAnim": "singRIGHT",
					"noteType": "",
					"mustPress": false
				},
				{
					"strumTime": 43000,
					"sustain": 0,
					"direction": 2,
					"noteAnim": "singUP",
					"noteType": "",
					"mustPress": false
				},
				{
					"strumTime": 43375,
					"sustain": 0,
					"direction": 3,
					"noteAnim": "singRIGHT",
					"noteType": "",
					"mustPress": false
				},
				{
					"strumTime": 43750,
					"sustain": 0,
					"direction": 3,
					"noteAnim": "singRIGHT",
					"noteType": "",
					"mustPress": false
				}
			]
		},
		{
			"length": 16,
			"notes": [
				{
					"strumTime": 44000,
					"sustain": 0,
					"direction": 1,
					"noteAnim": "singDOWN",
					"noteType": "",
					"mustPress": true
				},
				{
					"strumTime": 44500,
					"sustain": 0,
					"direction": 2,
					"noteAnim": "singUP",
					"noteType": "",
					"mustPress": true
				},
				{
					"strumTime": 44750,
					"sustain": 0,
					"direction": 3,
					"noteAnim": "singRIGHT",
					"noteType": "",
					"mustPress": true
				},
				{
					"strumTime": 45000,
					"sustain": 0,
					"direction": 2,
					"noteAnim": "singUP",
					"noteType": "",
					"mustPress": true
				},
				{
					"strumTime": 45375,
					"sustain": 0,
					"direction": 1,
					"noteAnim": "singDOWN",
					"noteType": "",
					"mustPress": true
				},
				{
					"strumTime": 45750,
					"sustain": 0,
					"direction": 3,
					"noteAnim": "singRIGHT",
					"noteType": "",
					"mustPress": true
				}
			]
		},
		{
			"length": 16,
			"notes": [
				{
					"strumTime": 46000,
					"sustain": 0,
					"direction": 1,
					"noteAnim": "singDOWN",
					"noteType": "",
					"mustPress": true
				},
				{
					"strumTime": 46500,
					"sustain": 0,
					"direction": 2,
					"noteAnim": "singUP",
					"noteType": "",
					"mustPress": true
				},
				{
					"strumTime": 46750,
					"sustain": 0,
					"direction": 3,
					"noteAnim": "singRIGHT",
					"noteType": "",
					"mustPress": true
				},
				{
					"strumTime": 47000,
					"sustain": 0,
					"direction": 2,
					"noteAnim": "singUP",
					"noteType": "",
					"mustPress": true
				},
				{
					"strumTime": 47375,
					"sustain": 0,
					"direction": 3,
					"noteAnim": "singRIGHT",
					"noteType": "",
					"mustPress": true
				},
				{
					"strumTime": 47750,
					"sustain": 0,
					"direction": 3,
					"noteAnim": "singRIGHT",
					"noteType": "",
					"mustPress": true
				}
			]
		},
		{
			"length": 16,
			"notes": [
				{
					"strumTime": 48000,
					"sustain": 0,
					"direction": 2,
					"noteAnim": "singUP",
					"noteType": "",
					"mustPress": false
				},
				{
					"strumTime": 48625,
					"sustain": 0,
					"direction": 0,
					"noteAnim": "singLEFT",
					"noteType": "",
					"mustPress": false
				},
				{
					"strumTime": 48875,
					"sustain": 0,
					"direction": 0,
					"noteAnim": "singLEFT",
					"noteType": "",
					"mustPress": false
				},
				{
					"strumTime": 49125,
					"sustain": 0,
					"direction": 3,
					"noteAnim": "singRIGHT",
					"noteType": "",
					"mustPress": false
				},
				{
					"strumTime": 49375,
					"sustain": 0,
					"direction": 3,
					"noteAnim": "singRIGHT",
					"noteType": "",
					"mustPress": false
				},
				{
					"strumTime": 49500,
					"sustain": 375,
					"direction": 0,
					"noteAnim": "singLEFT",
					"noteType": "",
					"mustPress": false
				}
			]
		},
		{
			"length": 16,
			"notes": [
				{
					"strumTime": 50000,
					"sustain": 0,
					"direction": 2,
					"noteAnim": "singUP",
					"noteType": "",
					"mustPress": false
				},
				{
					"strumTime": 50750,
					"sustain": 0,
					"direction": 2,
					"noteAnim": "singUP",
					"noteType": "",
					"mustPress": false
				},
				{
					"strumTime": 50875,
					"sustain": 0,
					"direction": 0,
					"noteAnim": "singLEFT",
					"noteType": "",
					"mustPress": false
				},
				{
					"strumTime": 51250,
					"sustain": 0,
					"direction": 3,
					"noteAnim": "singRIGHT",
					"noteType": "",
					"mustPress": false
				},
				{
					"strumTime": 51375,
					"sustain": 0,
					"direction": 0,
					"noteAnim": "singLEFT",
					"noteType": "",
					"mustPress": false
				},
				{
					"strumTime": 51500,
					"sustain": 0,
					"direction": 1,
					"noteAnim": "singDOWN",
					"noteType": "",
					"mustPress": false
				}
			]
		},
		{
			"length": 16,
			"notes": [
				{
					"strumTime": 52000,
					"sustain": 0,
					"direction": 2,
					"noteAnim": "singUP",
					"noteType": "",
					"mustPress": true
				},
				{
					"strumTime": 52625,
					"sustain": 0,
					"direction": 0,
					"noteAnim": "singLEFT",
					"noteType": "",
					"mustPress": true
				},
				{
					"strumTime": 52875,
					"sustain": 0,
					"direction": 0,
					"noteAnim": "singLEFT",
					"noteType": "",
					"mustPress": true
				},
				{
					"strumTime": 53125,
					"sustain": 0,
					"direction": 3,
					"noteAnim": "singRIGHT",
					"noteType": "",
					"mustPress": true
				},
				{
					"strumTime": 53375,
					"sustain": 0,
					"direction": 3,
					"noteAnim": "singRIGHT",
					"noteType": "",
					"mustPress": true
				},
				{
					"strumTime": 53500,
					"sustain": 375,
					"direction": 0,
					"noteAnim": "singLEFT",
					"noteType": "",
					"mustPress": true
				}
			]
		},
		{
			"length": 16,
			"notes": [
				{
					"strumTime": 54000,
					"sustain": 0,
					"direction": 2,
					"noteAnim": "singUP",
					"noteType": "",
					"mustPress": true
				},
				{
					"strumTime": 54750,
					"sustain": 0,
					"direction": 2,
					"noteAnim": "singUP",
					"noteType": "",
					"mustPress": true
				},
				{
					"strumTime": 54875,
					"sustain": 0,
					"direction": 0,
					"noteAnim": "singLEFT",
					"noteType": "",
					"mustPress": true
				},
				{
					"strumTime": 55250,
					"sustain": 0,
					"direction": 3,
					"noteAnim": "singRIGHT",
					"noteType": "",
					"mustPress": true
				},
				{
					"strumTime": 55375,
					"sustain": 0,
					"direction": 0,
					"noteAnim": "singLEFT",
					"noteType": "",
					"mustPress": true
				},
				{
					"strumTime": 55500,
					"sustain": 0,
					"direction": 1,
					"noteAnim": "singDOWN",
					"noteType": "",
					"mustPress": true
				}
			]
		},
		{
			"length": 16,
			"notes": [
				{
					"strumTime": 56000,
					"sustain": 0,
					"direction": 0,
					"noteAnim": "singLEFT",
					"noteType": "",
					"mustPress": false
				},
				{
					"strumTime": 56375,
					"sustain": 0,
					"direction": 0,
					"noteAnim": "singLEFT",
					"noteType": "",
					"mustPress": false
				},
				{
					"strumTime": 56500,
					"sustain": 0,
					"direction": 3,
					"noteAnim": "singRIGHT",
					"noteType": "",
					"mustPress": false
				},
				{
					"strumTime": 57000,
					"sustain": 0,
					"direction": 0,
					"noteAnim": "singLEFT",
					"noteType": "",
					"mustPress": false
				},
				{
					"strumTime": 57375,
					"sustain": 0,
					"direction": 0,
					"noteAnim": "singLEFT",
					"noteType": "",
					"mustPress": false
				},
				{
					"strumTime": 57500,
					"sustain": 0,
					"direction": 3,
					"noteAnim": "singRIGHT",
					"noteType": "",
					"mustPress": false
				}
			]
		},
		{
			"length": 16,
			"notes": [
				{
					"strumTime": 58000,
					"sustain": 0,
					"direction": 0,
					"noteAnim": "singLEFT",
					"noteType": "",
					"mustPress": false
				},
				{
					"strumTime": 58375,
					"sustain": 0,
					"direction": 0,
					"noteAnim": "singLEFT",
					"noteType": "",
					"mustPress": false
				},
				{
					"strumTime": 58500,
					"sustain": 0,
					"direction": 3,
					"noteAnim": "singRIGHT",
					"noteType": "",
					"mustPress": false
				},
				{
					"strumTime": 59000,
					"sustain": 0,
					"direction": 0,
					"noteAnim": "singLEFT",
					"noteType": "",
					"mustPress": false
				},
				{
					"strumTime": 59375,
					"sustain": 0,
					"direction": 0,
					"noteAnim": "singLEFT",
					"noteType": "",
					"mustPress": false
				},
				{
					"strumTime": 59500,
					"sustain": 0,
					"direction": 3,
					"noteAnim": "singRIGHT",
					"noteType": "",
					"mustPress": false
				}
			]
		},
		{
			"length": 16,
			"notes": [
				{
					"strumTime": 60000,
					"sustain": 0,
					"direction": 0,
					"noteAnim": "singLEFT",
					"noteType": "",
					"mustPress": true
				},
				{
					"strumTime": 60375,
					"sustain": 0,
					"direction": 0,
					"noteAnim": "singLEFT",
					"noteType": "",
					"mustPress": true
				},
				{
					"strumTime": 60500,
					"sustain": 0,
					"direction": 3,
					"noteAnim": "singRIGHT",
					"noteType": "",
					"mustPress": true
				},
				{
					"strumTime": 61000,
					"sustain": 0,
					"direction": 0,
					"noteAnim": "singLEFT",
					"noteType": "",
					"mustPress": true
				},
				{
					"strumTime": 61375,
					"sustain": 0,
					"direction": 0,
					"noteAnim": "singLEFT",
					"noteType": "",
					"mustPress": true
				},
				{
					"strumTime": 61500,
					"sustain": 0,
					"direction": 3,
					"noteAnim": "singRIGHT",
					"noteType": "",
					"mustPress": true
				}
			]
		},
		{
			"length": 16,
			"notes": [
				{
					"strumTime": 62000,
					"sustain": 0,
					"direction": 0,
					"noteAnim": "singLEFT",
					"noteType": "",
					"mustPress": true
				},
				{
					"strumTime": 62375,
					"sustain": 0,
					"direction": 0,
					"noteAnim": "singLEFT",
					"noteType": "",
					"mustPress": true
				},
				{
					"strumTime": 62500,
					"sustain": 0,
					"direction": 3,
					"noteAnim": "singRIGHT",
					"noteType": "",
					"mustPress": true
				},
				{
					"strumTime": 63000,
					"sustain": 0,
					"direction": 0,
					"noteAnim": "singLEFT",
					"noteType": "",
					"mustPress": true
				},
				{
					"strumTime": 63375,
					"sustain": 0,
					"direction": 0,
					"noteAnim": "singLEFT",
					"noteType": "",
					"mustPress": true
				},
				{
					"strumTime": 63500,
					"sustain": 0,
					"direction": 3,
					"noteAnim": "singRIGHT",
					"noteType": "",
					"mustPress": true
				}
			]
		},
		{
			"length": 16,
			"notes": [
				{
					"strumTime": 64500.0039,
					"sustain": 0,
					"direction": 3,
					"noteAnim": "singRIGHT",
					"noteType": "",
					"mustPress": false
				},
				{
					"strumTime": 65000.0039,
					"sustain": 250,
					"direction": 0,
					"noteAnim": "singLEFT",
					"noteType": "",
					"mustPress": false
				},
				{
					"strumTime": 65375.0039,
					"sustain": 0,
					"direction": 1,
					"noteAnim": "singDOWN",
					"noteType": "",
					"mustPress": false
				},
				{
					"strumTime": 65875,
					"sustain": 0,
					"direction": 2,
					"noteAnim": "singUP",
					"noteType": "",
					"mustPress": false
				}
			]
		},
		{
			"length": 16,
			"notes": [
				{
					"strumTime": 66375,
					"sustain": 0,
					"direction": 2,
					"noteAnim": "singUP",
					"noteType": "",
					"mustPress": false
				},
				{
					"strumTime": 67000,
					"sustain": 250,
					"direction": 3,
					"noteAnim": "singRIGHT",
					"noteType": "",
					"mustPress": false
				},
				{
					"strumTime": 67375,
					"sustain": 0,
					"direction": 3,
					"noteAnim": "singRIGHT",
					"noteType": "",
					"mustPress": false
				},
				{
					"strumTime": 67625,
					"sustain": 0,
					"direction": 0,
					"noteAnim": "singLEFT",
					"noteType": "",
					"mustPress": false
				}
			]
		},
		{
			"length": 16,
			"notes": [
				{
					"strumTime": 68500,
					"sustain": 0,
					"direction": 3,
					"noteAnim": "singRIGHT",
					"noteType": "",
					"mustPress": true
				},
				{
					"strumTime": 69000,
					"sustain": 250,
					"direction": 0,
					"noteAnim": "singLEFT",
					"noteType": "",
					"mustPress": true
				},
				{
					"strumTime": 69375,
					"sustain": 0,
					"direction": 1,
					"noteAnim": "singDOWN",
					"noteType": "",
					"mustPress": true
				},
				{
					"strumTime": 69875,
					"sustain": 0,
					"direction": 2,
					"noteAnim": "singUP",
					"noteType": "",
					"mustPress": true
				}
			]
		},
		{
			"length": 16,
			"notes": [
				{
					"strumTime": 70375,
					"sustain": 0,
					"direction": 2,
					"noteAnim": "singUP",
					"noteType": "",
					"mustPress": true
				},
				{
					"strumTime": 71000,
					"sustain": 250,
					"direction": 3,
					"noteAnim": "singRIGHT",
					"noteType": "",
					"mustPress": true
				},
				{
					"strumTime": 71375,
					"sustain": 0,
					"direction": 3,
					"noteAnim": "singRIGHT",
					"noteType": "",
					"mustPress": true
				},
				{
					"strumTime": 71625,
					"sustain": 0,
					"direction": 0,
					"noteAnim": "singLEFT",
					"noteType": "",
					"mustPress": true
				}
			]
		},
		{
			"length": 16,
			"notes": [
				{
					"strumTime": 72000,
					"sustain": 125,
					"direction": 2,
					"noteAnim": "singUP",
					"noteType": "",
					"mustPress": false
				},
				{
					"strumTime": 72500,
					"sustain": 0,
					"direction": 2,
					"noteAnim": "singUP",
					"noteType": "",
					"mustPress": false
				},
				{
					"strumTime": 72875,
					"sustain": 250,
					"direction": 3,
					"noteAnim": "singRIGHT",
					"noteType": "",
					"mustPress": false
				},
				{
					"strumTime": 73500,
					"sustain": 0,
					"direction": 0,
					"noteAnim": "singLEFT",
					"noteType": "",
					"mustPress": false
				},
				{
					"strumTime": 73875,
					"sustain": 250,
					"direction": 3,
					"noteAnim": "singRIGHT",
					"noteType": "",
					"mustPress": false
				}
			]
		},
		{
			"length": 16,
			"notes": [
				{
					"strumTime": 74250,
					"sustain": 0,
					"direction": 1,
					"noteAnim": "singDOWN",
					"noteType": "",
					"mustPress": false
				},
				{
					"strumTime": 74500,
					"sustain": 0,
					"direction": 3,
					"noteAnim": "singRIGHT",
					"noteType": "",
					"mustPress": false
				},
				{
					"strumTime": 74875,
					"sustain": 250,
					"direction": 3,
					"noteAnim": "singRIGHT",
					"noteType": "",
					"mustPress": false
				},
				{
					"strumTime": 75250,
					"sustain": 0,
					"direction": 1,
					"noteAnim": "singDOWN",
					"noteType": "",
					"mustPress": false
				},
				{
					"strumTime": 75500,
					"sustain": 0,
					"direction": 0,
					"noteAnim": "singLEFT",
					"noteType": "",
					"mustPress": false
				},
				{
					"strumTime": 75750,
					"sustain": 0,
					"direction": 3,
					"noteAnim": "singRIGHT",
					"noteType": "",
					"mustPress": false
				}
			]
		},
		{
			"length": 16,
			"notes": [
				{
					"strumTime": 76000,
					"sustain": 125,
					"direction": 2,
					"noteAnim": "singUP",
					"noteType": "",
					"mustPress": true
				},
				{
					"strumTime": 76500,
					"sustain": 0,
					"direction": 2,
					"noteAnim": "singUP",
					"noteType": "",
					"mustPress": true
				},
				{
					"strumTime": 76875,
					"sustain": 250,
					"direction": 3,
					"noteAnim": "singRIGHT",
					"noteType": "",
					"mustPress": true
				},
				{
					"strumTime": 77500,
					"sustain": 0,
					"direction": 0,
					"noteAnim": "singLEFT",
					"noteType": "",
					"mustPress": true
				},
				{
					"strumTime": 77875,
					"sustain": 250,
					"direction": 3,
					"noteAnim": "singRIGHT",
					"noteType": "",
					"mustPress": true
				}
			]
		},
		{
			"length": 16,
			"notes": [
				{
					"strumTime": 78250,
					"sustain": 0,
					"direction": 1,
					"noteAnim": "singDOWN",
					"noteType": "",
					"mustPress": true
				},
				{
					"strumTime": 78500,
					"sustain": 0,
					"direction": 3,
					"noteAnim": "singRIGHT",
					"noteType": "",
					"mustPress": true
				},
				{
					"strumTime": 78875,
					"sustain": 250,
					"direction": 3,
					"noteAnim": "singRIGHT",
					"noteType": "",
					"mustPress": true
				},
				{
					"strumTime": 79250,
					"sustain": 0,
					"direction": 1,
					"noteAnim": "singDOWN",
					"noteType": "",
					"mustPress": true
				},
				{
					"strumTime": 79500,
					"sustain": 0,
					"direction": 0,
					"noteAnim": "singLEFT",
					"noteType": "",
					"mustPress": true
				},
				{
					"strumTime": 79750,
					"sustain": 0,
					"direction": 3,
					"noteAnim": "singRIGHT",
					"noteType": "",
					"mustPress": true
				}
			]
		},
		{
			"length": 16,
			"notes": [
				{
					"strumTime": 80000,
					"sustain": 0,
					"direction": 0,
					"noteAnim": "singLEFT",
					"noteType": "",
					"mustPress": false
				},
				{
					"strumTime": 80375,
					"sustain": 0,
					"direction": 0,
					"noteAnim": "singLEFT",
					"noteType": "",
					"mustPress": false
				},
				{
					"strumTime": 80500,
					"sustain": 0,
					"direction": 3,
					"noteAnim": "singRIGHT",
					"noteType": "",
					"mustPress": false
				},
				{
					"strumTime": 81000,
					"sustain": 0,
					"direction": 0,
					"noteAnim": "singLEFT",
					"noteType": "",
					"mustPress": false
				},
				{
					"strumTime": 81375,
					"sustain": 0,
					"direction": 0,
					"noteAnim": "singLEFT",
					"noteType": "",
					"mustPress": false
				},
				{
					"strumTime": 81500,
					"sustain": 0,
					"direction": 3,
					"noteAnim": "singRIGHT",
					"noteType": "",
					"mustPress": false
				}
			]
		},
		{
			"length": 16,
			"notes": [
				{
					"strumTime": 82000,
					"sustain": 0,
					"direction": 0,
					"noteAnim": "singLEFT",
					"noteType": "",
					"mustPress": false
				},
				{
					"strumTime": 82375,
					"sustain": 0,
					"direction": 0,
					"noteAnim": "singLEFT",
					"noteType": "",
					"mustPress": false
				},
				{
					"strumTime": 82500,
					"sustain": 0,
					"direction": 3,
					"noteAnim": "singRIGHT",
					"noteType": "",
					"mustPress": false
				},
				{
					"strumTime": 83000,
					"sustain": 0,
					"direction": 0,
					"noteAnim": "singLEFT",
					"noteType": "",
					"mustPress": false
				},
				{
					"strumTime": 83375,
					"sustain": 0,
					"direction": 0,
					"noteAnim": "singLEFT",
					"noteType": "",
					"mustPress": false
				},
				{
					"strumTime": 83500,
					"sustain": 0,
					"direction": 3,
					"noteAnim": "singRIGHT",
					"noteType": "",
					"mustPress": false
				}
			]
		},
		{
			"length": 16,
			"notes": [
				{
					"strumTime": 84000,
					"sustain": 0,
					"direction": 0,
					"noteAnim": "singLEFT",
					"noteType": "",
					"mustPress": true
				},
				{
					"strumTime": 84375,
					"sustain": 0,
					"direction": 0,
					"noteAnim": "singLEFT",
					"noteType": "",
					"mustPress": true
				},
				{
					"strumTime": 84500,
					"sustain": 0,
					"direction": 3,
					"noteAnim": "singRIGHT",
					"noteType": "",
					"mustPress": true
				},
				{
					"strumTime": 85000,
					"sustain": 0,
					"direction": 0,
					"noteAnim": "singLEFT",
					"noteType": "",
					"mustPress": true
				},
				{
					"strumTime": 85375,
					"sustain": 0,
					"direction": 0,
					"noteAnim": "singLEFT",
					"noteType": "",
					"mustPress": true
				},
				{
					"strumTime": 85500,
					"sustain": 0,
					"direction": 3,
					"noteAnim": "singRIGHT",
					"noteType": "",
					"mustPress": true
				}
			]
		},
		{
			"length": 16,
			"notes": [
				{
					"strumTime": 86000,
					"sustain": 0,
					"direction": 0,
					"noteAnim": "singLEFT",
					"noteType": "",
					"mustPress": true
				},
				{
					"strumTime": 86375,
					"sustain": 0,
					"direction": 0,
					"noteAnim": "singLEFT",
					"noteType": "",
					"mustPress": true
				},
				{
					"strumTime": 86500,
					"sustain": 0,
					"direction": 3,
					"noteAnim": "singRIGHT",
					"noteType": "",
					"mustPress": true
				},
				{
					"strumTime": 87000,
					"sustain": 0,
					"direction": 0,
					"noteAnim": "singLEFT",
					"noteType": "",
					"mustPress": true
				},
				{
					"strumTime": 87375,
					"sustain": 0,
					"direction": 0,
					"noteAnim": "singLEFT",
					"noteType": "",
					"mustPress": true
				},
				{
					"strumTime": 87500,
					"sustain": 0,
					"direction": 3,
					"noteAnim": "singRIGHT",
					"noteType": "",
					"mustPress": true
				}
			]
		},
		{
			"length": 16,
			"notes": []
		},
		{
			"length": 16,
			"notes": []
		}
	],
	"song": "Roses",
	"bpmMapping": [],
	"extraData": {}
}