{
	"speed": 1,
	"spectator": "gf",
	"mustHitSections": [
		true,
		true,
		false,
		false,
		false,
		false,
		true,
		true,
		true,
		true,
		false,
		false,
		false,
		false,
		true,
		true,
		true,
		true,
		false,
		false,
		false,
		false,
		true,
		true,
		true,
		true,
		false,
		false,
		false,
		false,
		true,
		true,
		true,
		true,
		false,
		false,
		false,
		false,
		true,
		true,
		true,
		true,
		false,
		false,
		false,
		false,
		true,
		true,
		true,
		true,
		false,
		false,
		false,
		false,
		true,
		true,
		true,
		true,
		false,
		false,
		false,
		false,
		true,
		true,
		true,
		true,
		true,
		true,
		true,
		true,
		true,
		true,
		true,
		true
	],
	"opponent": "pico",
	"bpm": 175,
	"player": "bf",
	"sectionList": [
		{
			"length": 16,
			"notes": []
		},
		{
			"length": 16,
			"notes": []
		},
		{
			"length": 16,
			"notes": [
				{
					"strumTime": 2914.28564,
					"sustain": 0,
					"direction": 2,
					"noteAnim": "singUP",
					"noteType": "",
					"mustPress": false
				},
				{
					"strumTime": 3428.57129,
					"sustain": 257.142853,
					"direction": 1,
					"noteAnim": "singDOWN",
					"noteType": "",
					"mustPress": false
				},
				{
					"strumTime": 3771.42847,
					"sustain": 171.428574,
					"direction": 3,
					"noteAnim": "singRIGHT",
					"noteType": "",
					"mustPress": false
				}
			]
		},
		{
			"length": 16,
			"notes": [
				{
					"strumTime": 4285.71436,
					"sustain": 0,
					"direction": 2,
					"noteAnim": "singUP",
					"noteType": "",
					"mustPress": false
				},
				{
					"strumTime": 4800,
					"sustain": 257.142853,
					"direction": 1,
					"noteAnim": "singDOWN",
					"noteType": "",
					"mustPress": false
				},
				{
					"strumTime": 5142.857,
					"sustain": 171.428574,
					"direction": 3,
					"noteAnim": "singRIGHT",
					"noteType": "",
					"mustPress": false
				}
			]
		},
		{
			"length": 16,
			"notes": [
				{
					"strumTime": 5657.14258,
					"sustain": 0,
					"direction": 2,
					"noteAnim": "singUP",
					"noteType": "",
					"mustPress": false
				},
				{
					"strumTime": 6171.42871,
					"sustain": 257.142853,
					"direction": 1,
					"noteAnim": "singDOWN",
					"noteType": "",
					"mustPress": false
				},
				{
					"strumTime": 6514.28564,
					"sustain": 171.428574,
					"direction": 3,
					"noteAnim": "singRIGHT",
					"noteType": "",
					"mustPress": false
				}
			]
		},
		{
			"length": 16,
			"notes": [
				{
					"strumTime": 6857.14258,
					"sustain": 0,
					"direction": 0,
					"noteAnim": "singLEFT",
					"noteType": "",
					"mustPress": false
				},
				{
					"strumTime": 7200,
					"sustain": 0,
					"direction": 2,
					"noteAnim": "singUP",
					"noteType": "",
					"mustPress": false
				},
				{
					"strumTime": 7542.857,
					"sustain": 0,
					"direction": 2,
					"noteAnim": "singUP",
					"noteType": "",
					"mustPress": false
				},
				{
					"strumTime": 7885.71436,
					"sustain": 0,
					"direction": 0,
					"noteAnim": "singLEFT",
					"noteType": "",
					"mustPress": false
				}
			]
		},
		{
			"length": 16,
			"notes": [
				{
					"strumTime": 8400,
					"sustain": 0,
					"direction": 2,
					"noteAnim": "singUP",
					"noteType": "",
					"mustPress": true
				},
				{
					"strumTime": 8914.285,
					"sustain": 257.142853,
					"direction": 1,
					"noteAnim": "singDOWN",
					"noteType": "",
					"mustPress": true
				},
				{
					"strumTime": 9257.143,
					"sustain": 171.428574,
					"direction": 3,
					"noteAnim": "singRIGHT",
					"noteType": "",
					"mustPress": true
				}
			]
		},
		{
			"length": 16,
			"notes": [
				{
					"strumTime": 9771.429,
					"sustain": 0,
					"direction": 2,
					"noteAnim": "singUP",
					"noteType": "",
					"mustPress": true
				},
				{
					"strumTime": 10285.7139,
					"sustain": 257.142853,
					"direction": 1,
					"noteAnim": "singDOWN",
					"noteType": "",
					"mustPress": true
				},
				{
					"strumTime": 10628.5713,
					"sustain": 171.428574,
					"direction": 3,
					"noteAnim": "singRIGHT",
					"noteType": "",
					"mustPress": true
				}
			]
		},
		{
			"length": 16,
			"notes": [
				{
					"strumTime": 11142.8574,
					"sustain": 0,
					"direction": 2,
					"noteAnim": "singUP",
					"noteType": "",
					"mustPress": true
				},
				{
					"strumTime": 11657.1426,
					"sustain": 257.142853,
					"direction": 1,
					"noteAnim": "singDOWN",
					"noteType": "",
					"mustPress": true
				},
				{
					"strumTime": 12000,
					"sustain": 171.428574,
					"direction": 3,
					"noteAnim": "singRIGHT",
					"noteType": "",
					"mustPress": true
				}
			]
		},
		{
			"length": 16,
			"notes": [
				{
					"strumTime": 12342.8574,
					"sustain": 0,
					"direction": 0,
					"noteAnim": "singLEFT",
					"noteType": "",
					"mustPress": true
				},
				{
					"strumTime": 12685.7139,
					"sustain": 0,
					"direction": 2,
					"noteAnim": "singUP",
					"noteType": "",
					"mustPress": true
				},
				{
					"strumTime": 13028.5713,
					"sustain": 0,
					"direction": 2,
					"noteAnim": "singUP",
					"noteType": "",
					"mustPress": true
				},
				{
					"strumTime": 13371.4287,
					"sustain": 0,
					"direction": 0,
					"noteAnim": "singLEFT",
					"noteType": "",
					"mustPress": true
				}
			]
		},
		{
			"length": 16,
			"notes": [
				{
					"strumTime": 14057.1426,
					"sustain": 0,
					"direction": 2,
					"noteAnim": "singUP",
					"noteType": "",
					"mustPress": false
				},
				{
					"strumTime": 14400,
					"sustain": 0,
					"direction": 0,
					"noteAnim": "singLEFT",
					"noteType": "",
					"mustPress": false
				}
			]
		},
		{
			"length": 16,
			"notes": [
				{
					"strumTime": 15428.5713,
					"sustain": 0,
					"direction": 3,
					"noteAnim": "singRIGHT",
					"noteType": "",
					"mustPress": false
				},
				{
					"strumTime": 15771.4287,
					"sustain": 0,
					"direction": 2,
					"noteAnim": "singUP",
					"noteType": "",
					"mustPress": false
				},
				{
					"strumTime": 16285.7139,
					"sustain": 0,
					"direction": 1,
					"noteAnim": "singDOWN",
					"noteType": "",
					"mustPress": false
				}
			]
		},
		{
			"length": 16,
			"notes": [
				{
					"strumTime": 16800,
					"sustain": 0,
					"direction": 3,
					"noteAnim": "singRIGHT",
					"noteType": "",
					"mustPress": false
				},
				{
					"strumTime": 17142.8574,
					"sustain": 0,
					"direction": 0,
					"noteAnim": "singLEFT",
					"noteType": "",
					"mustPress": false
				},
				{
					"strumTime": 17485.7148,
					"sustain": 0,
					"direction": 3,
					"noteAnim": "singRIGHT",
					"noteType": "",
					"mustPress": false
				}
			]
		},
		{
			"length": 16,
			"notes": [
				{
					"strumTime": 17828.57,
					"sustain": 0,
					"direction": 3,
					"noteAnim": "singRIGHT",
					"noteType": "",
					"mustPress": false
				},
				{
					"strumTime": 18171.4277,
					"sustain": 0,
					"direction": 1,
					"noteAnim": "singDOWN",
					"noteType": "",
					"mustPress": false
				},
				{
					"strumTime": 18514.2852,
					"sustain": 0,
					"direction": 3,
					"noteAnim": "singRIGHT",
					"noteType": "",
					"mustPress": false
				}
			]
		},
		{
			"length": 16,
			"notes": [
				{
					"strumTime": 19542.8574,
					"sustain": 0,
					"direction": 2,
					"noteAnim": "singUP",
					"noteType": "",
					"mustPress": true
				},
				{
					"strumTime": 19885.7148,
					"sustain": 0,
					"direction": 0,
					"noteAnim": "singLEFT",
					"noteType": "",
					"mustPress": true
				}
			]
		},
		{
			"length": 16,
			"notes": [
				{
					"strumTime": 20914.2852,
					"sustain": 0,
					"direction": 3,
					"noteAnim": "singRIGHT",
					"noteType": "",
					"mustPress": true
				},
				{
					"strumTime": 21257.1426,
					"sustain": 0,
					"direction": 2,
					"noteAnim": "singUP",
					"noteType": "",
					"mustPress": true
				},
				{
					"strumTime": 21771.4277,
					"sustain": 0,
					"direction": 1,
					"noteAnim": "singDOWN",
					"noteType": "",
					"mustPress": true
				}
			]
		},
		{
			"length": 16,
			"notes": [
				{
					"strumTime": 22285.7148,
					"sustain": 0,
					"direction": 3,
					"noteAnim": "singRIGHT",
					"noteType": "",
					"mustPress": true
				},
				{
					"strumTime": 22628.57,
					"sustain": 0,
					"direction": 0,
					"noteAnim": "singLEFT",
					"noteType": "",
					"mustPress": true
				},
				{
					"strumTime": 22971.4277,
					"sustain": 0,
					"direction": 3,
					"noteAnim": "singRIGHT",
					"noteType": "",
					"mustPress": true
				}
			]
		},
		{
			"length": 16,
			"notes": [
				{
					"strumTime": 23314.2852,
					"sustain": 0,
					"direction": 3,
					"noteAnim": "singRIGHT",
					"noteType": "",
					"mustPress": true
				},
				{
					"strumTime": 23657.1426,
					"sustain": 0,
					"direction": 1,
					"noteAnim": "singDOWN",
					"noteType": "",
					"mustPress": true
				},
				{
					"strumTime": 24000,
					"sustain": 0,
					"direction": 3,
					"noteAnim": "singRIGHT",
					"noteType": "",
					"mustPress": true
				}
			]
		},
		{
			"length": 16,
			"notes": [
				{
					"strumTime": 24685.7148,
					"sustain": 0,
					"direction": 2,
					"noteAnim": "singUP",
					"noteType": "",
					"mustPress": false
				},
				{
					"strumTime": 25371.4277,
					"sustain": 0,
					"direction": 0,
					"noteAnim": "singLEFT",
					"noteType": "",
					"mustPress": false
				},
				{
					"strumTime": 25714.2852,
					"sustain": 0,
					"direction": 3,
					"noteAnim": "singRIGHT",
					"noteType": "",
					"mustPress": false
				}
			]
		},
		{
			"length": 16,
			"notes": [
				{
					"strumTime": 26400,
					"sustain": 0,
					"direction": 3,
					"noteAnim": "singRIGHT",
					"noteType": "",
					"mustPress": false
				},
				{
					"strumTime": 26742.8574,
					"sustain": 0,
					"direction": 2,
					"noteAnim": "singUP",
					"noteType": "",
					"mustPress": false
				},
				{
					"strumTime": 27257.1426,
					"sustain": 0,
					"direction": 1,
					"noteAnim": "singDOWN",
					"noteType": "",
					"mustPress": false
				}
			]
		},
		{
			"length": 16,
			"notes": [
				{
					"strumTime": 27771.4277,
					"sustain": 0,
					"direction": 3,
					"noteAnim": "singRIGHT",
					"noteType": "",
					"mustPress": false
				},
				{
					"strumTime": 28114.2852,
					"sustain": 0,
					"direction": 0,
					"noteAnim": "singLEFT",
					"noteType": "",
					"mustPress": false
				},
				{
					"strumTime": 28457.1426,
					"sustain": 0,
					"direction": 3,
					"noteAnim": "singRIGHT",
					"noteType": "",
					"mustPress": false
				}
			]
		},
		{
			"length": 16,
			"notes": [
				{
					"strumTime": 28800,
					"sustain": 0,
					"direction": 3,
					"noteAnim": "singRIGHT",
					"noteType": "",
					"mustPress": false
				},
				{
					"strumTime": 29142.8574,
					"sustain": 0,
					"direction": 1,
					"noteAnim": "singDOWN",
					"noteType": "",
					"mustPress": false
				},
				{
					"strumTime": 29485.7148,
					"sustain": 0,
					"direction": 3,
					"noteAnim": "singRIGHT",
					"noteType": "",
					"mustPress": false
				}
			]
		},
		{
			"length": 16,
			"notes": [
				{
					"strumTime": 30171.4277,
					"sustain": 0,
					"direction": 2,
					"noteAnim": "singUP",
					"noteType": "",
					"mustPress": true
				},
				{
					"strumTime": 30857.1426,
					"sustain": 0,
					"direction": 0,
					"noteAnim": "singLEFT",
					"noteType": "",
					"mustPress": true
				},
				{
					"strumTime": 31200,
					"sustain": 0,
					"direction": 3,
					"noteAnim": "singRIGHT",
					"noteType": "",
					"mustPress": true
				}
			]
		},
		{
			"length": 16,
			"notes": [
				{
					"strumTime": 31885.7148,
					"sustain": 0,
					"direction": 3,
					"noteAnim": "singRIGHT",
					"noteType": "",
					"mustPress": true
				},
				{
					"strumTime": 32228.57,
					"sustain": 0,
					"direction": 2,
					"noteAnim": "singUP",
					"noteType": "",
					"mustPress": true
				},
				{
					"strumTime": 32742.8574,
					"sustain": 0,
					"direction": 1,
					"noteAnim": "singDOWN",
					"noteType": "",
					"mustPress": true
				}
			]
		},
		{
			"length": 16,
			"notes": [
				{
					"strumTime": 33257.14,
					"sustain": 0,
					"direction": 3,
					"noteAnim": "singRIGHT",
					"noteType": "",
					"mustPress": true
				},
				{
					"strumTime": 33600,
					"sustain": 0,
					"direction": 0,
					"noteAnim": "singLEFT",
					"noteType": "",
					"mustPress": true
				},
				{
					"strumTime": 33942.8555,
					"sustain": 0,
					"direction": 3,
					"noteAnim": "singRIGHT",
					"noteType": "",
					"mustPress": true
				}
			]
		},
		{
			"length": 16,
			"notes": [
				{
					"strumTime": 34285.7148,
					"sustain": 0,
					"direction": 3,
					"noteAnim": "singRIGHT",
					"noteType": "",
					"mustPress": true
				},
				{
					"strumTime": 34628.57,
					"sustain": 0,
					"direction": 1,
					"noteAnim": "singDOWN",
					"noteType": "",
					"mustPress": true
				},
				{
					"strumTime": 34971.43,
					"sustain": 0,
					"direction": 3,
					"noteAnim": "singRIGHT",
					"noteType": "",
					"mustPress": true
				}
			]
		},
		{
			"length": 16,
			"notes": [
				{
					"strumTime": 35657.14,
					"sustain": 0,
					"direction": 2,
					"noteAnim": "singUP",
					"noteType": "",
					"mustPress": false
				},
				{
					"strumTime": 36342.8555,
					"sustain": 0,
					"direction": 2,
					"noteAnim": "singUP",
					"noteType": "",
					"mustPress": false
				},
				{
					"strumTime": 36685.7148,
					"sustain": 0,
					"direction": 0,
					"noteAnim": "singLEFT",
					"noteType": "",
					"mustPress": false
				}
			]
		},
		{
			"length": 16,
			"notes": [
				{
					"strumTime": 37028.57,
					"sustain": 0,
					"direction": 2,
					"noteAnim": "singUP",
					"noteType": "",
					"mustPress": false
				},
				{
					"strumTime": 37714.2852,
					"sustain": 0,
					"direction": 2,
					"noteAnim": "singUP",
					"noteType": "",
					"mustPress": false
				},
				{
					"strumTime": 38057.14,
					"sustain": 0,
					"direction": 0,
					"noteAnim": "singLEFT",
					"noteType": "",
					"mustPress": false
				}
			]
		},
		{
			"length": 16,
			"notes": [
				{
					"strumTime": 38400,
					"sustain": 0,
					"direction": 2,
					"noteAnim": "singUP",
					"noteType": "",
					"mustPress": false
				},
				{
					"strumTime": 39085.7148,
					"sustain": 0,
					"direction": 2,
					"noteAnim": "singUP",
					"noteType": "",
					"mustPress": false
				},
				{
					"strumTime": 39428.57,
					"sustain": 0,
					"direction": 0,
					"noteAnim": "singLEFT",
					"noteType": "",
					"mustPress": false
				}
			]
		},
		{
			"length": 16,
			"notes": [
				{
					"strumTime": 39771.43,
					"sustain": 0,
					"direction": 2,
					"noteAnim": "singUP",
					"noteType": "",
					"mustPress": false
				},
				{
					"strumTime": 40457.14,
					"sustain": 0,
					"direction": 2,
					"noteAnim": "singUP",
					"noteType": "",
					"mustPress": false
				},
				{
					"strumTime": 40800,
					"sustain": 0,
					"direction": 0,
					"noteAnim": "singLEFT",
					"noteType": "",
					"mustPress": false
				}
			]
		},
		{
			"length": 16,
			"notes": [
				{
					"strumTime": 41142.8555,
					"sustain": 0,
					"direction": 2,
					"noteAnim": "singUP",
					"noteType": "",
					"mustPress": true
				},
				{
					"strumTime": 41828.57,
					"sustain": 0,
					"direction": 2,
					"noteAnim": "singUP",
					"noteType": "",
					"mustPress": true
				},
				{
					"strumTime": 42171.43,
					"sustain": 0,
					"direction": 0,
					"noteAnim": "singLEFT",
					"noteType": "",
					"mustPress": true
				}
			]
		},
		{
			"length": 16,
			"notes": [
				{
					"strumTime": 42514.2852,
					"sustain": 0,
					"direction": 2,
					"noteAnim": "singUP",
					"noteType": "",
					"mustPress": true
				},
				{
					"strumTime": 43200,
					"sustain": 0,
					"direction": 2,
					"noteAnim": "singUP",
					"noteType": "",
					"mustPress": true
				},
				{
					"strumTime": 43542.8555,
					"sustain": 0,
					"direction": 0,
					"noteAnim": "singLEFT",
					"noteType": "",
					"mustPress": true
				}
			]
		},
		{
			"length": 16,
			"notes": [
				{
					"strumTime": 43885.7148,
					"sustain": 0,
					"direction": 2,
					"noteAnim": "singUP",
					"noteType": "",
					"mustPress": true
				},
				{
					"strumTime": 44571.43,
					"sustain": 0,
					"direction": 2,
					"noteAnim": "singUP",
					"noteType": "",
					"mustPress": true
				},
				{
					"strumTime": 44914.2852,
					"sustain": 0,
					"direction": 0,
					"noteAnim": "singLEFT",
					"noteType": "",
					"mustPress": true
				}
			]
		},
		{
			"length": 16,
			"notes": [
				{
					"strumTime": 45257.14,
					"sustain": 0,
					"direction": 2,
					"noteAnim": "singUP",
					"noteType": "",
					"mustPress": true
				},
				{
					"strumTime": 45942.8555,
					"sustain": 0,
					"direction": 2,
					"noteAnim": "singUP",
					"noteType": "",
					"mustPress": true
				},
				{
					"strumTime": 46285.7148,
					"sustain": 0,
					"direction": 0,
					"noteAnim": "singLEFT",
					"noteType": "",
					"mustPress": true
				}
			]
		},
		{
			"length": 16,
			"notes": [
				{
					"strumTime": 46628.57,
					"sustain": 0,
					"direction": 2,
					"noteAnim": "singUP",
					"noteType": "",
					"mustPress": false
				},
				{
					"strumTime": 47314.2852,
					"sustain": 0,
					"direction": 2,
					"noteAnim": "singUP",
					"noteType": "",
					"mustPress": false
				},
				{
					"strumTime": 47657.14,
					"sustain": 0,
					"direction": 0,
					"noteAnim": "singLEFT",
					"noteType": "",
					"mustPress": false
				}
			]
		},
		{
			"length": 16,
			"notes": [
				{
					"strumTime": 48000,
					"sustain": 0,
					"direction": 2,
					"noteAnim": "singUP",
					"noteType": "",
					"mustPress": false
				},
				{
					"strumTime": 48685.7148,
					"sustain": 0,
					"direction": 2,
					"noteAnim": "singUP",
					"noteType": "",
					"mustPress": false
				},
				{
					"strumTime": 49028.57,
					"sustain": 0,
					"direction": 0,
					"noteAnim": "singLEFT",
					"noteType": "",
					"mustPress": false
				}
			]
		},
		{
			"length": 16,
			"notes": [
				{
					"strumTime": 49371.43,
					"sustain": 0,
					"direction": 2,
					"noteAnim": "singUP",
					"noteType": "",
					"mustPress": false
				},
				{
					"strumTime": 50057.14,
					"sustain": 0,
					"direction": 2,
					"noteAnim": "singUP",
					"noteType": "",
					"mustPress": false
				},
				{
					"strumTime": 50400,
					"sustain": 0,
					"direction": 0,
					"noteAnim": "singLEFT",
					"noteType": "",
					"mustPress": false
				}
			]
		},
		{
			"length": 16,
			"notes": [
				{
					"strumTime": 50742.8555,
					"sustain": 0,
					"direction": 3,
					"noteAnim": "singRIGHT",
					"noteType": "",
					"mustPress": false
				},
				{
					"strumTime": 51428.57,
					"sustain": 0,
					"direction": 2,
					"noteAnim": "singUP",
					"noteType": "",
					"mustPress": false
				},
				{
					"strumTime": 51771.43,
					"sustain": 0,
					"direction": 0,
					"noteAnim": "singLEFT",
					"noteType": "",
					"mustPress": false
				}
			]
		},
		{
			"length": 16,
			"notes": [
				{
					"strumTime": 52114.2852,
					"sustain": 0,
					"direction": 2,
					"noteAnim": "singUP",
					"noteType": "",
					"mustPress": true
				},
				{
					"strumTime": 52800,
					"sustain": 0,
					"direction": 2,
					"noteAnim": "singUP",
					"noteType": "",
					"mustPress": true
				},
				{
					"strumTime": 53142.8555,
					"sustain": 0,
					"direction": 0,
					"noteAnim": "singLEFT",
					"noteType": "",
					"mustPress": true
				}
			]
		},
		{
			"length": 16,
			"notes": [
				{
					"strumTime": 53485.7148,
					"sustain": 0,
					"direction": 2,
					"noteAnim": "singUP",
					"noteType": "",
					"mustPress": true
				},
				{
					"strumTime": 54171.43,
					"sustain": 0,
					"direction": 2,
					"noteAnim": "singUP",
					"noteType": "",
					"mustPress": true
				},
				{
					"strumTime": 54514.2852,
					"sustain": 0,
					"direction": 0,
					"noteAnim": "singLEFT",
					"noteType": "",
					"mustPress": true
				}
			]
		},
		{
			"length": 16,
			"notes": [
				{
					"strumTime": 54857.14,
					"sustain": 0,
					"direction": 2,
					"noteAnim": "singUP",
					"noteType": "",
					"mustPress": true
				},
				{
					"strumTime": 55542.8555,
					"sustain": 0,
					"direction": 2,
					"noteAnim": "singUP",
					"noteType": "",
					"mustPress": true
				},
				{
					"strumTime": 55885.7148,
					"sustain": 0,
					"direction": 0,
					"noteAnim": "singLEFT",
					"noteType": "",
					"mustPress": true
				}
			]
		},
		{
			"length": 16,
			"notes": [
				{
					"strumTime": 56228.57,
					"sustain": 0,
					"direction": 3,
					"noteAnim": "singRIGHT",
					"noteType": "",
					"mustPress": true
				},
				{
					"strumTime": 56914.2852,
					"sustain": 0,
					"direction": 2,
					"noteAnim": "singUP",
					"noteType": "",
					"mustPress": true
				},
				{
					"strumTime": 57257.14,
					"sustain": 0,
					"direction": 0,
					"noteAnim": "singLEFT",
					"noteType": "",
					"mustPress": true
				}
			]
		},
		{
			"length": 16,
			"notes": [
				{
					"strumTime": 57600,
					"sustain": 0,
					"direction": 3,
					"noteAnim": "singRIGHT",
					"noteType": "",
					"mustPress": false
				},
				{
					"strumTime": 58285.7148,
					"sustain": 0,
					"direction": 2,
					"noteAnim": "singUP",
					"noteType": "",
					"mustPress": false
				}
			]
		},
		{
			"length": 16,
			"notes": [
				{
					"strumTime": 58971.43,
					"sustain": 0,
					"direction": 2,
					"noteAnim": "singUP",
					"noteType": "",
					"mustPress": false
				},
				{
					"strumTime": 59314.2852,
					"sustain": 0,
					"direction": 3,
					"noteAnim": "singRIGHT",
					"noteType": "",
					"mustPress": false
				},
				{
					"strumTime": 59657.14,
					"sustain": 0,
					"direction": 2,
					"noteAnim": "singUP",
					"noteType": "",
					"mustPress": false
				}
			]
		},
		{
			"length": 16,
			"notes": [
				{
					"strumTime": 60342.8555,
					"sustain": 0,
					"direction": 3,
					"noteAnim": "singRIGHT",
					"noteType": "",
					"mustPress": false
				},
				{
					"strumTime": 61028.57,
					"sustain": 0,
					"direction": 2,
					"noteAnim": "singUP",
					"noteType": "",
					"mustPress": false
				},
				{
					"strumTime": 61542.8555,
					"sustain": 0,
					"direction": 0,
					"noteAnim": "singLEFT",
					"noteType": "",
					"mustPress": false
				}
			]
		},
		{
			"length": 16,
			"notes": [
				{
					"strumTime": 61714.2852,
					"sustain": 0,
					"direction": 2,
					"noteAnim": "singUP",
					"noteType": "",
					"mustPress": false
				},
				{
					"strumTime": 62057.14,
					"sustain": 0,
					"direction": 0,
					"noteAnim": "singLEFT",
					"noteType": "",
					"mustPress": false
				},
				{
					"strumTime": 62400,
					"sustain": 0,
					"direction": 2,
					"noteAnim": "singUP",
					"noteType": "",
					"mustPress": false
				},
				{
					"strumTime": 62742.8555,
					"sustain": 0,
					"direction": 0,
					"noteAnim": "singLEFT",
					"noteType": "",
					"mustPress": false
				}
			]
		},
		{
			"length": 16,
			"notes": [
				{
					"strumTime": 63085.7148,
					"sustain": 0,
					"direction": 3,
					"noteAnim": "singRIGHT",
					"noteType": "",
					"mustPress": true
				},
				{
					"strumTime": 63771.43,
					"sustain": 0,
					"direction": 2,
					"noteAnim": "singUP",
					"noteType": "",
					"mustPress": true
				}
			]
		},
		{
			"length": 16,
			"notes": [
				{
					"strumTime": 64457.14,
					"sustain": 0,
					"direction": 2,
					"noteAnim": "singUP",
					"noteType": "",
					"mustPress": true
				},
				{
					"strumTime": 64800,
					"sustain": 0,
					"direction": 3,
					"noteAnim": "singRIGHT",
					"noteType": "",
					"mustPress": true
				},
				{
					"strumTime": 65142.8555,
					"sustain": 0,
					"direction": 2,
					"noteAnim": "singUP",
					"noteType": "",
					"mustPress": true
				}
			]
		},
		{
			"length": 16,
			"notes": [
				{
					"strumTime": 65828.57,
					"sustain": 0,
					"direction": 3,
					"noteAnim": "singRIGHT",
					"noteType": "",
					"mustPress": true
				},
				{
					"strumTime": 66514.28,
					"sustain": 0,
					"direction": 2,
					"noteAnim": "singUP",
					"noteType": "",
					"mustPress": true
				},
				{
					"strumTime": 67028.57,
					"sustain": 0,
					"direction": 0,
					"noteAnim": "singLEFT",
					"noteType": "",
					"mustPress": true
				}
			]
		},
		{
			"length": 16,
			"notes": [
				{
					"strumTime": 67200,
					"sustain": 0,
					"direction": 2,
					"noteAnim": "singUP",
					"noteType": "",
					"mustPress": true
				},
				{
					"strumTime": 67542.86,
					"sustain": 0,
					"direction": 0,
					"noteAnim": "singLEFT",
					"noteType": "",
					"mustPress": true
				},
				{
					"strumTime": 67885.71,
					"sustain": 0,
					"direction": 2,
					"noteAnim": "singUP",
					"noteType": "",
					"mustPress": true
				},
				{
					"strumTime": 68228.57,
					"sustain": 0,
					"direction": 0,
					"noteAnim": "singLEFT",
					"noteType": "",
					"mustPress": true
				}
			]
		},
		{
			"length": 16,
			"notes": [
				{
					"strumTime": 68571.43,
					"sustain": 0,
					"direction": 2,
					"noteAnim": "singUP",
					"noteType": "",
					"mustPress": false
				},
				{
					"strumTime": 69257.14,
					"sustain": 0,
					"direction": 2,
					"noteAnim": "singUP",
					"noteType": "",
					"mustPress": false
				}
			]
		},
		{
			"length": 16,
			"notes": [
				{
					"strumTime": 69942.86,
					"sustain": 0,
					"direction": 0,
					"noteAnim": "singLEFT",
					"noteType": "",
					"mustPress": false
				},
				{
					"strumTime": 70628.57,
					"sustain": 0,
					"direction": 2,
					"noteAnim": "singUP",
					"noteType": "",
					"mustPress": false
				}
			]
		},
		{
			"length": 16,
			"notes": [
				{
					"strumTime": 71314.28,
					"sustain": 0,
					"direction": 3,
					"noteAnim": "singRIGHT",
					"noteType": "",
					"mustPress": false
				},
				{
					"strumTime": 72000,
					"sustain": 0,
					"direction": 2,
					"noteAnim": "singUP",
					"noteType": "",
					"mustPress": false
				},
				{
					"strumTime": 72342.86,
					"sustain": 0,
					"direction": 0,
					"noteAnim": "singLEFT",
					"noteType": "",
					"mustPress": false
				}
			]
		},
		{
			"length": 16,
			"notes": [
				{
					"strumTime": 72685.71,
					"sustain": 0,
					"direction": 3,
					"noteAnim": "singRIGHT",
					"noteType": "",
					"mustPress": false
				},
				{
					"strumTime": 73371.43,
					"sustain": 0,
					"direction": 2,
					"noteAnim": "singUP",
					"noteType": "",
					"mustPress": false
				},
				{
					"strumTime": 73714.28,
					"sustain": 0,
					"direction": 0,
					"noteAnim": "singLEFT",
					"noteType": "",
					"mustPress": false
				}
			]
		},
		{
			"length": 16,
			"notes": [
				{
					"strumTime": 74057.14,
					"sustain": 0,
					"direction": 2,
					"noteAnim": "singUP",
					"noteType": "",
					"mustPress": true
				},
				{
					"strumTime": 74742.86,
					"sustain": 0,
					"direction": 2,
					"noteAnim": "singUP",
					"noteType": "",
					"mustPress": true
				}
			]
		},
		{
			"length": 16,
			"notes": [
				{
					"strumTime": 75428.57,
					"sustain": 0,
					"direction": 0,
					"noteAnim": "singLEFT",
					"noteType": "",
					"mustPress": true
				},
				{
					"strumTime": 76114.28,
					"sustain": 0,
					"direction": 2,
					"noteAnim": "singUP",
					"noteType": "",
					"mustPress": true
				}
			]
		},
		{
			"length": 16,
			"notes": [
				{
					"strumTime": 76800,
					"sustain": 0,
					"direction": 3,
					"noteAnim": "singRIGHT",
					"noteType": "",
					"mustPress": true
				},
				{
					"strumTime": 77485.71,
					"sustain": 0,
					"direction": 2,
					"noteAnim": "singUP",
					"noteType": "",
					"mustPress": true
				},
				{
					"strumTime": 77828.57,
					"sustain": 0,
					"direction": 0,
					"noteAnim": "singLEFT",
					"noteType": "",
					"mustPress": true
				}
			]
		},
		{
			"length": 16,
			"notes": [
				{
					"strumTime": 78171.43,
					"sustain": 0,
					"direction": 3,
					"noteAnim": "singRIGHT",
					"noteType": "",
					"mustPress": true
				},
				{
					"strumTime": 78857.14,
					"sustain": 0,
					"direction": 2,
					"noteAnim": "singUP",
					"noteType": "",
					"mustPress": true
				},
				{
					"strumTime": 79200,
					"sustain": 0,
					"direction": 0,
					"noteAnim": "singLEFT",
					"noteType": "",
					"mustPress": true
				}
			]
		},
		{
			"length": 16,
			"notes": [
				{
					"strumTime": 79542.86,
					"sustain": 0,
					"direction": 2,
					"noteAnim": "singUP",
					"noteType": "",
					"mustPress": false
				},
				{
					"strumTime": 80228.57,
					"sustain": 0,
					"direction": 2,
					"noteAnim": "singUP",
					"noteType": "",
					"mustPress": false
				},
				{
					"strumTime": 80571.43,
					"sustain": 0,
					"direction": 0,
					"noteAnim": "singLEFT",
					"noteType": "",
					"mustPress": false
				}
			]
		},
		{
			"length": 16,
			"notes": [
				{
					"strumTime": 80914.28,
					"sustain": 0,
					"direction": 2,
					"noteAnim": "singUP",
					"noteType": "",
					"mustPress": false
				},
				{
					"strumTime": 81600,
					"sustain": 0,
					"direction": 2,
					"noteAnim": "singUP",
					"noteType": "",
					"mustPress": false
				},
				{
					"strumTime": 81942.86,
					"sustain": 0,
					"direction": 0,
					"noteAnim": "singLEFT",
					"noteType": "",
					"mustPress": false
				}
			]
		},
		{
			"length": 16,
			"notes": [
				{
					"strumTime": 82285.71,
					"sustain": 0,
					"direction": 2,
					"noteAnim": "singUP",
					"noteType": "",
					"mustPress": false
				},
				{
					"strumTime": 82971.43,
					"sustain": 0,
					"direction": 2,
					"noteAnim": "singUP",
					"noteType": "",
					"mustPress": false
				},
				{
					"strumTime": 83314.28,
					"sustain": 0,
					"direction": 0,
					"noteAnim": "singLEFT",
					"noteType": "",
					"mustPress": false
				}
			]
		},
		{
			"length": 16,
			"notes": [
				{
					"strumTime": 83657.14,
					"sustain": 0,
					"direction": 3,
					"noteAnim": "singRIGHT",
					"noteType": "",
					"mustPress": false
				},
				{
					"strumTime": 84342.86,
					"sustain": 0,
					"direction": 2,
					"noteAnim": "singUP",
					"noteType": "",
					"mustPress": false
				},
				{
					"strumTime": 84685.71,
					"sustain": 0,
					"direction": 0,
					"noteAnim": "singLEFT",
					"noteType": "",
					"mustPress": false
				}
			]
		},
		{
			"length": 16,
			"notes": [
				{
					"strumTime": 85028.57,
					"sustain": 0,
					"direction": 2,
					"noteAnim": "singUP",
					"noteType": "",
					"mustPress": true
				},
				{
					"strumTime": 85714.28,
					"sustain": 0,
					"direction": 2,
					"noteAnim": "singUP",
					"noteType": "",
					"mustPress": true
				},
				{
					"strumTime": 86057.14,
					"sustain": 0,
					"direction": 0,
					"noteAnim": "singLEFT",
					"noteType": "",
					"mustPress": true
				}
			]
		},
		{
			"length": 16,
			"notes": [
				{
					"strumTime": 86400,
					"sustain": 0,
					"direction": 2,
					"noteAnim": "singUP",
					"noteType": "",
					"mustPress": true
				},
				{
					"strumTime": 87085.71,
					"sustain": 0,
					"direction": 2,
					"noteAnim": "singUP",
					"noteType": "",
					"mustPress": true
				},
				{
					"strumTime": 87428.57,
					"sustain": 0,
					"direction": 0,
					"noteAnim": "singLEFT",
					"noteType": "",
					"mustPress": true
				}
			]
		},
		{
			"length": 16,
			"notes": [
				{
					"strumTime": 87771.43,
					"sustain": 0,
					"direction": 2,
					"noteAnim": "singUP",
					"noteType": "",
					"mustPress": true
				},
				{
					"strumTime": 88457.14,
					"sustain": 0,
					"direction": 2,
					"noteAnim": "singUP",
					"noteType": "",
					"mustPress": true
				},
				{
					"strumTime": 88800,
					"sustain": 0,
					"direction": 0,
					"noteAnim": "singLEFT",
					"noteType": "",
					"mustPress": true
				}
			]
		},
		{
			"length": 16,
			"notes": [
				{
					"strumTime": 89142.86,
					"sustain": 0,
					"direction": 3,
					"noteAnim": "singRIGHT",
					"noteType": "",
					"mustPress": true
				},
				{
					"strumTime": 89828.57,
					"sustain": 0,
					"direction": 2,
					"noteAnim": "singUP",
					"noteType": "",
					"mustPress": true
				},
				{
					"strumTime": 90171.43,
					"sustain": 0,
					"direction": 0,
					"noteAnim": "singLEFT",
					"noteType": "",
					"mustPress": true
				},
				{
					"strumTime": 90342.86,
					"sustain": 0,
					"direction": 0,
					"noteAnim": "singLEFT",
					"noteType": "",
					"mustPress": true
				}
			]
		},
		{
			"length": 16,
			"notes": [
				{
					"strumTime": 90514.28,
					"sustain": 0,
					"direction": 1,
					"noteAnim": "singDOWN",
					"noteType": "",
					"mustPress": true
				}
			]
		},
		{
			"length": 16,
			"notes": []
		},
		{
			"length": 16,
			"notes": []
		},
		{
			"length": 16,
			"notes": []
		},
		{
			"length": 16,
			"notes": []
		},
		{
			"length": 16,
			"notes": []
		},
		{
			"length": 16,
			"notes": []
		},
		{
			"length": 16,
			"notes": []
		}
	],
	"song": "Philly Nice",
	"bpmMapping": [],
	"extraData": {}
}