{
	"speed": 1.5,
	"spectator": "gf",
	"mustHitSections": [
		true,
		true,
		true,
		true,
		true,
		true,
		true,
		true,
		false,
		false,
		true,
		true,
		false,
		false,
		true,
		true,
		false,
		false,
		false,
		false,
		true,
		true,
		true,
		true,
		false,
		false,
		false,
		false,
		false,
		false,
		false,
		false,
		true,
		true,
		true,
		true,
		true,
		true,
		true,
		true,
		false,
		false,
		true,
		true,
		false,
		false,
		true,
		true,
		false,
		false,
		false,
		false,
		true,
		true,
		true,
		true,
		false,
		false,
		true,
		true,
		false,
		false,
		true,
		true,
		true
	],
	"opponent": "dad",
	"bpm": 180,
	"player": "bf",
	"sectionList": [
		{
			"length": 16,
			"notes": []
		},
		{
			"length": 16,
			"notes": []
		},
		{
			"length": 16,
			"notes": []
		},
		{
			"length": 16,
			"notes": []
		},
		{
			"length": 16,
			"notes": []
		},
		{
			"length": 16,
			"notes": []
		},
		{
			"length": 16,
			"notes": []
		},
		{
			"length": 16,
			"notes": []
		},
		{
			"length": 16,
			"notes": [
				{
					"strumTime": 10666.667,
					"sustain": 0,
					"direction": 2,
					"noteAnim": "singUP",
					"noteType": "",
					"mustPress": false
				},
				{
					"strumTime": 11000,
					"sustain": 0,
					"direction": 0,
					"noteAnim": "singLEFT",
					"noteType": "",
					"mustPress": false
				},
				{
					"strumTime": 11333.334,
					"sustain": 0,
					"direction": 2,
					"noteAnim": "singUP",
					"noteType": "",
					"mustPress": false
				},
				{
					"strumTime": 11666.667,
					"sustain": 0,
					"direction": 0,
					"noteAnim": "singLEFT",
					"noteType": "",
					"mustPress": false
				},
				{
					"strumTime": 11833.334,
					"sustain": 0,
					"direction": 3,
					"noteAnim": "singRIGHT",
					"noteType": "",
					"mustPress": false
				}
			]
		},
		{
			"length": 16,
			"notes": [
				{
					"strumTime": 12000,
					"sustain": 0,
					"direction": 2,
					"noteAnim": "singUP",
					"noteType": "",
					"mustPress": false
				},
				{
					"strumTime": 12166.667,
					"sustain": 0,
					"direction": 3,
					"noteAnim": "singRIGHT",
					"noteType": "",
					"mustPress": false
				},
				{
					"strumTime": 12333.334,
					"sustain": 0,
					"direction": 0,
					"noteAnim": "singLEFT",
					"noteType": "",
					"mustPress": false
				},
				{
					"strumTime": 12666.667,
					"sustain": 0,
					"direction": 2,
					"noteAnim": "singUP",
					"noteType": "",
					"mustPress": false
				},
				{
					"strumTime": 13000,
					"sustain": 0,
					"direction": 0,
					"noteAnim": "singLEFT",
					"noteType": "",
					"mustPress": false
				},
				{
					"strumTime": 13166.667,
					"sustain": 0,
					"direction": 3,
					"noteAnim": "singRIGHT",
					"noteType": "",
					"mustPress": false
				}
			]
		},
		{
			"length": 16,
			"notes": [
				{
					"strumTime": 13333.334,
					"sustain": 0,
					"direction": 2,
					"noteAnim": "singUP",
					"noteType": "",
					"mustPress": true
				},
				{
					"strumTime": 13666.667,
					"sustain": 0,
					"direction": 0,
					"noteAnim": "singLEFT",
					"noteType": "",
					"mustPress": true
				},
				{
					"strumTime": 14000,
					"sustain": 0,
					"direction": 2,
					"noteAnim": "singUP",
					"noteType": "",
					"mustPress": true
				},
				{
					"strumTime": 14333.334,
					"sustain": 0,
					"direction": 0,
					"noteAnim": "singLEFT",
					"noteType": "",
					"mustPress": true
				},
				{
					"strumTime": 14500,
					"sustain": 0,
					"direction": 3,
					"noteAnim": "singRIGHT",
					"noteType": "",
					"mustPress": true
				}
			]
		},
		{
			"length": 16,
			"notes": [
				{
					"strumTime": 14666.667,
					"sustain": 0,
					"direction": 2,
					"noteAnim": "singUP",
					"noteType": "",
					"mustPress": true
				},
				{
					"strumTime": 14833.334,
					"sustain": 0,
					"direction": 3,
					"noteAnim": "singRIGHT",
					"noteType": "",
					"mustPress": true
				},
				{
					"strumTime": 15000,
					"sustain": 0,
					"direction": 0,
					"noteAnim": "singLEFT",
					"noteType": "",
					"mustPress": true
				},
				{
					"strumTime": 15333.334,
					"sustain": 0,
					"direction": 2,
					"noteAnim": "singUP",
					"noteType": "",
					"mustPress": true
				},
				{
					"strumTime": 15666.667,
					"sustain": 0,
					"direction": 0,
					"noteAnim": "singLEFT",
					"noteType": "",
					"mustPress": true
				},
				{
					"strumTime": 15833.334,
					"sustain": 0,
					"direction": 3,
					"noteAnim": "singRIGHT",
					"noteType": "",
					"mustPress": true
				}
			]
		},
		{
			"length": 16,
			"notes": [
				{
					"strumTime": 16000,
					"sustain": 0,
					"direction": 1,
					"noteAnim": "singDOWN",
					"noteType": "",
					"mustPress": false
				},
				{
					"strumTime": 16333.334,
					"sustain": 0,
					"direction": 0,
					"noteAnim": "singLEFT",
					"noteType": "",
					"mustPress": false
				},
				{
					"strumTime": 16500,
					"sustain": 0,
					"direction": 3,
					"noteAnim": "singRIGHT",
					"noteType": "",
					"mustPress": false
				},
				{
					"strumTime": 16666.668,
					"sustain": 0,
					"direction": 1,
					"noteAnim": "singDOWN",
					"noteType": "",
					"mustPress": false
				}
			]
		},
		{
			"length": 16,
			"notes": [
				{
					"strumTime": 17333.334,
					"sustain": 0,
					"direction": 1,
					"noteAnim": "singDOWN",
					"noteType": "",
					"mustPress": false
				},
				{
					"strumTime": 17666.668,
					"sustain": 0,
					"direction": 0,
					"noteAnim": "singLEFT",
					"noteType": "",
					"mustPress": false
				},
				{
					"strumTime": 17833.334,
					"sustain": 0,
					"direction": 0,
					"noteAnim": "singLEFT",
					"noteType": "",
					"mustPress": false
				},
				{
					"strumTime": 18000,
					"sustain": 0,
					"direction": 3,
					"noteAnim": "singRIGHT",
					"noteType": "",
					"mustPress": false
				},
				{
					"strumTime": 18166.668,
					"sustain": 0,
					"direction": 3,
					"noteAnim": "singRIGHT",
					"noteType": "",
					"mustPress": false
				},
				{
					"strumTime": 18333.334,
					"sustain": 0,
					"direction": 3,
					"noteAnim": "singRIGHT",
					"noteType": "",
					"mustPress": false
				},
				{
					"strumTime": 18500,
					"sustain": 0,
					"direction": 3,
					"noteAnim": "singRIGHT",
					"noteType": "",
					"mustPress": false
				}
			]
		},
		{
			"length": 16,
			"notes": [
				{
					"strumTime": 18666.668,
					"sustain": 0,
					"direction": 1,
					"noteAnim": "singDOWN",
					"noteType": "",
					"mustPress": true
				},
				{
					"strumTime": 19000,
					"sustain": 0,
					"direction": 0,
					"noteAnim": "singLEFT",
					"noteType": "",
					"mustPress": true
				},
				{
					"strumTime": 19166.668,
					"sustain": 0,
					"direction": 3,
					"noteAnim": "singRIGHT",
					"noteType": "",
					"mustPress": true
				},
				{
					"strumTime": 19333.334,
					"sustain": 0,
					"direction": 1,
					"noteAnim": "singDOWN",
					"noteType": "",
					"mustPress": true
				}
			]
		},
		{
			"length": 16,
			"notes": [
				{
					"strumTime": 20000,
					"sustain": 0,
					"direction": 1,
					"noteAnim": "singDOWN",
					"noteType": "",
					"mustPress": true
				},
				{
					"strumTime": 20333.334,
					"sustain": 0,
					"direction": 0,
					"noteAnim": "singLEFT",
					"noteType": "",
					"mustPress": true
				},
				{
					"strumTime": 20500,
					"sustain": 0,
					"direction": 0,
					"noteAnim": "singLEFT",
					"noteType": "",
					"mustPress": true
				},
				{
					"strumTime": 20666.668,
					"sustain": 0,
					"direction": 3,
					"noteAnim": "singRIGHT",
					"noteType": "",
					"mustPress": true
				},
				{
					"strumTime": 20833.334,
					"sustain": 0,
					"direction": 3,
					"noteAnim": "singRIGHT",
					"noteType": "",
					"mustPress": true
				},
				{
					"strumTime": 21000,
					"sustain": 0,
					"direction": 3,
					"noteAnim": "singRIGHT",
					"noteType": "",
					"mustPress": true
				},
				{
					"strumTime": 21166.668,
					"sustain": 0,
					"direction": 3,
					"noteAnim": "singRIGHT",
					"noteType": "",
					"mustPress": true
				}
			]
		},
		{
			"length": 16,
			"notes": [
				{
					"strumTime": 21666.668,
					"sustain": 0,
					"direction": 2,
					"noteAnim": "singUP",
					"noteType": "",
					"mustPress": false
				},
				{
					"strumTime": 22000,
					"sustain": 0,
					"direction": 3,
					"noteAnim": "singRIGHT",
					"noteType": "",
					"mustPress": false
				}
			]
		},
		{
			"length": 16,
			"notes": [
				{
					"strumTime": 22833.334,
					"sustain": 0,
					"direction": 1,
					"noteAnim": "singDOWN",
					"noteType": "",
					"mustPress": false
				},
				{
					"strumTime": 23000,
					"sustain": 0,
					"direction": 3,
					"noteAnim": "singRIGHT",
					"noteType": "",
					"mustPress": false
				},
				{
					"strumTime": 23333.334,
					"sustain": 0,
					"direction": 0,
					"noteAnim": "singLEFT",
					"noteType": "",
					"mustPress": false
				}
			]
		},
		{
			"length": 16,
			"notes": [
				{
					"strumTime": 24333.334,
					"sustain": 0,
					"direction": 2,
					"noteAnim": "singUP",
					"noteType": "",
					"mustPress": false
				},
				{
					"strumTime": 24666.668,
					"sustain": 0,
					"direction": 1,
					"noteAnim": "singDOWN",
					"noteType": "",
					"mustPress": false
				},
				{
					"strumTime": 25000,
					"sustain": 0,
					"direction": 0,
					"noteAnim": "singLEFT",
					"noteType": "",
					"mustPress": false
				}
			]
		},
		{
			"length": 16,
			"notes": [
				{
					"strumTime": 25333.334,
					"sustain": 0,
					"direction": 2,
					"noteAnim": "singUP",
					"noteType": "",
					"mustPress": false
				},
				{
					"strumTime": 25666.668,
					"sustain": 0,
					"direction": 0,
					"noteAnim": "singLEFT",
					"noteType": "",
					"mustPress": false
				},
				{
					"strumTime": 25833.334,
					"sustain": 0,
					"direction": 3,
					"noteAnim": "singRIGHT",
					"noteType": "",
					"mustPress": false
				},
				{
					"strumTime": 26000,
					"sustain": 0,
					"direction": 2,
					"noteAnim": "singUP",
					"noteType": "",
					"mustPress": false
				}
			]
		},
		{
			"length": 16,
			"notes": [
				{
					"strumTime": 27000,
					"sustain": 0,
					"direction": 2,
					"noteAnim": "singUP",
					"noteType": "",
					"mustPress": true
				},
				{
					"strumTime": 27333.334,
					"sustain": 0,
					"direction": 3,
					"noteAnim": "singRIGHT",
					"noteType": "",
					"mustPress": true
				}
			]
		},
		{
			"length": 16,
			"notes": [
				{
					"strumTime": 28166.668,
					"sustain": 0,
					"direction": 1,
					"noteAnim": "singDOWN",
					"noteType": "",
					"mustPress": true
				},
				{
					"strumTime": 28333.334,
					"sustain": 0,
					"direction": 3,
					"noteAnim": "singRIGHT",
					"noteType": "",
					"mustPress": true
				},
				{
					"strumTime": 28666.668,
					"sustain": 0,
					"direction": 0,
					"noteAnim": "singLEFT",
					"noteType": "",
					"mustPress": true
				}
			]
		},
		{
			"length": 16,
			"notes": [
				{
					"strumTime": 29666.668,
					"sustain": 0,
					"direction": 2,
					"noteAnim": "singUP",
					"noteType": "",
					"mustPress": true
				},
				{
					"strumTime": 30000,
					"sustain": 0,
					"direction": 1,
					"noteAnim": "singDOWN",
					"noteType": "",
					"mustPress": true
				},
				{
					"strumTime": 30333.334,
					"sustain": 0,
					"direction": 0,
					"noteAnim": "singLEFT",
					"noteType": "",
					"mustPress": true
				}
			]
		},
		{
			"length": 16,
			"notes": [
				{
					"strumTime": 30666.668,
					"sustain": 0,
					"direction": 0,
					"noteAnim": "singLEFT",
					"noteType": "",
					"mustPress": false
				},
				{
					"strumTime": 30666.668,
					"sustain": 0,
					"direction": 2,
					"noteAnim": "singUP",
					"noteType": "",
					"mustPress": true
				},
				{
					"strumTime": 30833.334,
					"sustain": 0,
					"direction": 1,
					"noteAnim": "singDOWN",
					"noteType": "",
					"mustPress": false
				},
				{
					"strumTime": 31000,
					"sustain": 0,
					"direction": 3,
					"noteAnim": "singRIGHT",
					"noteType": "",
					"mustPress": false
				},
				{
					"strumTime": 31000,
					"sustain": 0,
					"direction": 0,
					"noteAnim": "singLEFT",
					"noteType": "",
					"mustPress": true
				},
				{
					"strumTime": 31166.668,
					"sustain": 0,
					"direction": 1,
					"noteAnim": "singDOWN",
					"noteType": "",
					"mustPress": false
				},
				{
					"strumTime": 31166.668,
					"sustain": 0,
					"direction": 3,
					"noteAnim": "singRIGHT",
					"noteType": "",
					"mustPress": true
				},
				{
					"strumTime": 31333.334,
					"sustain": 0,
					"direction": 0,
					"noteAnim": "singLEFT",
					"noteType": "",
					"mustPress": false
				},
				{
					"strumTime": 31333.334,
					"sustain": 0,
					"direction": 2,
					"noteAnim": "singUP",
					"noteType": "",
					"mustPress": true
				},
				{
					"strumTime": 31500,
					"sustain": 0,
					"direction": 1,
					"noteAnim": "singDOWN",
					"noteType": "",
					"mustPress": false
				},
				{
					"strumTime": 31666.668,
					"sustain": 0,
					"direction": 3,
					"noteAnim": "singRIGHT",
					"noteType": "",
					"mustPress": false
				},
				{
					"strumTime": 31833.334,
					"sustain": 0,
					"direction": 1,
					"noteAnim": "singDOWN",
					"noteType": "",
					"mustPress": false
				}
			]
		},
		{
			"length": 16,
			"notes": [
				{
					"strumTime": 32166.668,
					"sustain": 0,
					"direction": 0,
					"noteAnim": "singLEFT",
					"noteType": "",
					"mustPress": false
				},
				{
					"strumTime": 32333.334,
					"sustain": 0,
					"direction": 3,
					"noteAnim": "singRIGHT",
					"noteType": "",
					"mustPress": false
				},
				{
					"strumTime": 32666.668,
					"sustain": 0,
					"direction": 1,
					"noteAnim": "singDOWN",
					"noteType": "",
					"mustPress": false
				},
				{
					"strumTime": 33000,
					"sustain": 0,
					"direction": 0,
					"noteAnim": "singLEFT",
					"noteType": "",
					"mustPress": false
				}
			]
		},
		{
			"length": 16,
			"notes": [
				{
					"strumTime": 33500,
					"sustain": 0,
					"direction": 2,
					"noteAnim": "singUP",
					"noteType": "",
					"mustPress": false
				},
				{
					"strumTime": 33666.668,
					"sustain": 0,
					"direction": 3,
					"noteAnim": "singRIGHT",
					"noteType": "",
					"mustPress": false
				},
				{
					"strumTime": 34000,
					"sustain": 0,
					"direction": 2,
					"noteAnim": "singUP",
					"noteType": "",
					"mustPress": false
				},
				{
					"strumTime": 34333.3359,
					"sustain": 0,
					"direction": 0,
					"noteAnim": "singLEFT",
					"noteType": "",
					"mustPress": false
				}
			]
		},
		{
			"length": 16,
			"notes": [
				{
					"strumTime": 34666.668,
					"sustain": 0,
					"direction": 0,
					"noteAnim": "singLEFT",
					"noteType": "",
					"mustPress": false
				},
				{
					"strumTime": 35000,
					"sustain": 0,
					"direction": 1,
					"noteAnim": "singDOWN",
					"noteType": "",
					"mustPress": false
				},
				{
					"strumTime": 35333.3359,
					"sustain": 0,
					"direction": 3,
					"noteAnim": "singRIGHT",
					"noteType": "",
					"mustPress": false
				},
				{
					"strumTime": 35666.668,
					"sustain": 0,
					"direction": 1,
					"noteAnim": "singDOWN",
					"noteType": "",
					"mustPress": false
				}
			]
		},
		{
			"length": 16,
			"notes": [
				{
					"strumTime": 36000,
					"sustain": 0,
					"direction": 2,
					"noteAnim": "singUP",
					"noteType": "",
					"mustPress": false
				},
				{
					"strumTime": 36333.3359,
					"sustain": 0,
					"direction": 3,
					"noteAnim": "singRIGHT",
					"noteType": "",
					"mustPress": false
				},
				{
					"strumTime": 36666.668,
					"sustain": 0,
					"direction": 0,
					"noteAnim": "singLEFT",
					"noteType": "",
					"mustPress": false
				}
			]
		},
		{
			"length": 16,
			"notes": [
				{
					"strumTime": 37500,
					"sustain": 0,
					"direction": 1,
					"noteAnim": "singDOWN",
					"noteType": "",
					"mustPress": false
				},
				{
					"strumTime": 37666.668,
					"sustain": 0,
					"direction": 3,
					"noteAnim": "singRIGHT",
					"noteType": "",
					"mustPress": false
				},
				{
					"strumTime": 38000,
					"sustain": 0,
					"direction": 0,
					"noteAnim": "singLEFT",
					"noteType": "",
					"mustPress": false
				},
				{
					"strumTime": 38333.3359,
					"sustain": 0,
					"direction": 1,
					"noteAnim": "singDOWN",
					"noteType": "",
					"mustPress": false
				}
			]
		},
		{
			"length": 16,
			"notes": [
				{
					"strumTime": 38666.668,
					"sustain": 0,
					"direction": 0,
					"noteAnim": "singLEFT",
					"noteType": "",
					"mustPress": false
				},
				{
					"strumTime": 39000,
					"sustain": 0,
					"direction": 1,
					"noteAnim": "singDOWN",
					"noteType": "",
					"mustPress": false
				},
				{
					"strumTime": 39333.3359,
					"sustain": 0,
					"direction": 2,
					"noteAnim": "singUP",
					"noteType": "",
					"mustPress": false
				},
				{
					"strumTime": 39500,
					"sustain": 0,
					"direction": 3,
					"noteAnim": "singRIGHT",
					"noteType": "",
					"mustPress": false
				},
				{
					"strumTime": 39666.668,
					"sustain": 0,
					"direction": 2,
					"noteAnim": "singUP",
					"noteType": "",
					"mustPress": false
				}
			]
		},
		{
			"length": 16,
			"notes": [
				{
					"strumTime": 40166.668,
					"sustain": 0,
					"direction": 0,
					"noteAnim": "singLEFT",
					"noteType": "",
					"mustPress": false
				},
				{
					"strumTime": 40333.3359,
					"sustain": 0,
					"direction": 3,
					"noteAnim": "singRIGHT",
					"noteType": "",
					"mustPress": false
				},
				{
					"strumTime": 40666.668,
					"sustain": 0,
					"direction": 2,
					"noteAnim": "singUP",
					"noteType": "",
					"mustPress": false
				},
				{
					"strumTime": 40833.3359,
					"sustain": 0,
					"direction": 3,
					"noteAnim": "singRIGHT",
					"noteType": "",
					"mustPress": false
				},
				{
					"strumTime": 41000,
					"sustain": 0,
					"direction": 2,
					"noteAnim": "singUP",
					"noteType": "",
					"mustPress": false
				}
			]
		},
		{
			"length": 16,
			"notes": [
				{
					"strumTime": 41333.3359,
					"sustain": 0,
					"direction": 0,
					"noteAnim": "singLEFT",
					"noteType": "",
					"mustPress": true
				},
				{
					"strumTime": 41333.3359,
					"sustain": 0,
					"direction": 0,
					"noteAnim": "singLEFT",
					"noteType": "",
					"mustPress": false
				},
				{
					"strumTime": 41500,
					"sustain": 0,
					"direction": 1,
					"noteAnim": "singDOWN",
					"noteType": "",
					"mustPress": true
				},
				{
					"strumTime": 41666.668,
					"sustain": 0,
					"direction": 3,
					"noteAnim": "singRIGHT",
					"noteType": "",
					"mustPress": true
				},
				{
					"strumTime": 41666.668,
					"sustain": 0,
					"direction": 2,
					"noteAnim": "singUP",
					"noteType": "",
					"mustPress": false
				},
				{
					"strumTime": 41833.3359,
					"sustain": 0,
					"direction": 1,
					"noteAnim": "singDOWN",
					"noteType": "",
					"mustPress": true
				},
				{
					"strumTime": 42000,
					"sustain": 0,
					"direction": 0,
					"noteAnim": "singLEFT",
					"noteType": "",
					"mustPress": true
				},
				{
					"strumTime": 42000,
					"sustain": 0,
					"direction": 3,
					"noteAnim": "singRIGHT",
					"noteType": "",
					"mustPress": false
				},
				{
					"strumTime": 42166.668,
					"sustain": 0,
					"direction": 1,
					"noteAnim": "singDOWN",
					"noteType": "",
					"mustPress": true
				},
				{
					"strumTime": 42333.3359,
					"sustain": 0,
					"direction": 3,
					"noteAnim": "singRIGHT",
					"noteType": "",
					"mustPress": true
				},
				{
					"strumTime": 42333.3359,
					"sustain": 0,
					"direction": 3,
					"noteAnim": "singRIGHT",
					"noteType": "",
					"mustPress": false
				},
				{
					"strumTime": 42500,
					"sustain": 0,
					"direction": 1,
					"noteAnim": "singDOWN",
					"noteType": "",
					"mustPress": true
				}
			]
		},
		{
			"length": 16,
			"notes": [
				{
					"strumTime": 42833.3359,
					"sustain": 0,
					"direction": 0,
					"noteAnim": "singLEFT",
					"noteType": "",
					"mustPress": true
				},
				{
					"strumTime": 43000,
					"sustain": 0,
					"direction": 3,
					"noteAnim": "singRIGHT",
					"noteType": "",
					"mustPress": true
				},
				{
					"strumTime": 43333.3359,
					"sustain": 0,
					"direction": 1,
					"noteAnim": "singDOWN",
					"noteType": "",
					"mustPress": true
				},
				{
					"strumTime": 43666.668,
					"sustain": 0,
					"direction": 0,
					"noteAnim": "singLEFT",
					"noteType": "",
					"mustPress": true
				}
			]
		},
		{
			"length": 16,
			"notes": [
				{
					"strumTime": 44166.668,
					"sustain": 0,
					"direction": 2,
					"noteAnim": "singUP",
					"noteType": "",
					"mustPress": true
				},
				{
					"strumTime": 44333.3359,
					"sustain": 0,
					"direction": 3,
					"noteAnim": "singRIGHT",
					"noteType": "",
					"mustPress": true
				},
				{
					"strumTime": 44666.668,
					"sustain": 0,
					"direction": 2,
					"noteAnim": "singUP",
					"noteType": "",
					"mustPress": true
				},
				{
					"strumTime": 45000,
					"sustain": 0,
					"direction": 0,
					"noteAnim": "singLEFT",
					"noteType": "",
					"mustPress": true
				}
			]
		},
		{
			"length": 16,
			"notes": [
				{
					"strumTime": 45333.3359,
					"sustain": 0,
					"direction": 0,
					"noteAnim": "singLEFT",
					"noteType": "",
					"mustPress": true
				},
				{
					"strumTime": 45666.668,
					"sustain": 0,
					"direction": 1,
					"noteAnim": "singDOWN",
					"noteType": "",
					"mustPress": true
				},
				{
					"strumTime": 46000,
					"sustain": 0,
					"direction": 3,
					"noteAnim": "singRIGHT",
					"noteType": "",
					"mustPress": true
				},
				{
					"strumTime": 46333.3359,
					"sustain": 0,
					"direction": 1,
					"noteAnim": "singDOWN",
					"noteType": "",
					"mustPress": true
				}
			]
		},
		{
			"length": 16,
			"notes": [
				{
					"strumTime": 46666.668,
					"sustain": 0,
					"direction": 2,
					"noteAnim": "singUP",
					"noteType": "",
					"mustPress": true
				},
				{
					"strumTime": 47000,
					"sustain": 0,
					"direction": 3,
					"noteAnim": "singRIGHT",
					"noteType": "",
					"mustPress": true
				},
				{
					"strumTime": 47333.3359,
					"sustain": 0,
					"direction": 0,
					"noteAnim": "singLEFT",
					"noteType": "",
					"mustPress": true
				}
			]
		},
		{
			"length": 16,
			"notes": [
				{
					"strumTime": 48166.668,
					"sustain": 0,
					"direction": 1,
					"noteAnim": "singDOWN",
					"noteType": "",
					"mustPress": true
				},
				{
					"strumTime": 48333.3359,
					"sustain": 0,
					"direction": 3,
					"noteAnim": "singRIGHT",
					"noteType": "",
					"mustPress": true
				},
				{
					"strumTime": 48666.668,
					"sustain": 0,
					"direction": 0,
					"noteAnim": "singLEFT",
					"noteType": "",
					"mustPress": true
				},
				{
					"strumTime": 49000,
					"sustain": 0,
					"direction": 1,
					"noteAnim": "singDOWN",
					"noteType": "",
					"mustPress": true
				}
			]
		},
		{
			"length": 16,
			"notes": [
				{
					"strumTime": 49333.3359,
					"sustain": 0,
					"direction": 0,
					"noteAnim": "singLEFT",
					"noteType": "",
					"mustPress": true
				},
				{
					"strumTime": 49666.668,
					"sustain": 0,
					"direction": 1,
					"noteAnim": "singDOWN",
					"noteType": "",
					"mustPress": true
				},
				{
					"strumTime": 50000,
					"sustain": 0,
					"direction": 2,
					"noteAnim": "singUP",
					"noteType": "",
					"mustPress": true
				},
				{
					"strumTime": 50166.668,
					"sustain": 0,
					"direction": 3,
					"noteAnim": "singRIGHT",
					"noteType": "",
					"mustPress": true
				},
				{
					"strumTime": 50333.3359,
					"sustain": 0,
					"direction": 2,
					"noteAnim": "singUP",
					"noteType": "",
					"mustPress": true
				}
			]
		},
		{
			"length": 16,
			"notes": [
				{
					"strumTime": 50833.3359,
					"sustain": 0,
					"direction": 0,
					"noteAnim": "singLEFT",
					"noteType": "",
					"mustPress": true
				},
				{
					"strumTime": 51000,
					"sustain": 0,
					"direction": 3,
					"noteAnim": "singRIGHT",
					"noteType": "",
					"mustPress": true
				},
				{
					"strumTime": 51333.3359,
					"sustain": 0,
					"direction": 2,
					"noteAnim": "singUP",
					"noteType": "",
					"mustPress": true
				},
				{
					"strumTime": 51500,
					"sustain": 0,
					"direction": 3,
					"noteAnim": "singRIGHT",
					"noteType": "",
					"mustPress": true
				},
				{
					"strumTime": 51666.668,
					"sustain": 0,
					"direction": 2,
					"noteAnim": "singUP",
					"noteType": "",
					"mustPress": true
				}
			]
		},
		{
			"length": 16,
			"notes": [
				{
					"strumTime": 52000,
					"sustain": 0,
					"direction": 0,
					"noteAnim": "singLEFT",
					"noteType": "",
					"mustPress": true
				},
				{
					"strumTime": 52333.3359,
					"sustain": 0,
					"direction": 2,
					"noteAnim": "singUP",
					"noteType": "",
					"mustPress": true
				},
				{
					"strumTime": 52666.668,
					"sustain": 0,
					"direction": 3,
					"noteAnim": "singRIGHT",
					"noteType": "",
					"mustPress": true
				},
				{
					"strumTime": 53000,
					"sustain": 0,
					"direction": 3,
					"noteAnim": "singRIGHT",
					"noteType": "",
					"mustPress": true
				}
			]
		},
		{
			"length": 16,
			"notes": [
				{
					"strumTime": 53333.3359,
					"sustain": 0,
					"direction": 2,
					"noteAnim": "singUP",
					"noteType": "",
					"mustPress": false
				},
				{
					"strumTime": 53666.668,
					"sustain": 0,
					"direction": 0,
					"noteAnim": "singLEFT",
					"noteType": "",
					"mustPress": false
				},
				{
					"strumTime": 54000,
					"sustain": 0,
					"direction": 2,
					"noteAnim": "singUP",
					"noteType": "",
					"mustPress": false
				},
				{
					"strumTime": 54333.3359,
					"sustain": 0,
					"direction": 0,
					"noteAnim": "singLEFT",
					"noteType": "",
					"mustPress": false
				},
				{
					"strumTime": 54500,
					"sustain": 0,
					"direction": 3,
					"noteAnim": "singRIGHT",
					"noteType": "",
					"mustPress": false
				}
			]
		},
		{
			"length": 16,
			"notes": [
				{
					"strumTime": 54666.668,
					"sustain": 0,
					"direction": 2,
					"noteAnim": "singUP",
					"noteType": "",
					"mustPress": false
				},
				{
					"strumTime": 55000,
					"sustain": 0,
					"direction": 0,
					"noteAnim": "singLEFT",
					"noteType": "",
					"mustPress": false
				},
				{
					"strumTime": 55333.3359,
					"sustain": 0,
					"direction": 2,
					"noteAnim": "singUP",
					"noteType": "",
					"mustPress": false
				},
				{
					"strumTime": 55666.668,
					"sustain": 0,
					"direction": 0,
					"noteAnim": "singLEFT",
					"noteType": "",
					"mustPress": false
				},
				{
					"strumTime": 55833.3359,
					"sustain": 0,
					"direction": 3,
					"noteAnim": "singRIGHT",
					"noteType": "",
					"mustPress": false
				}
			]
		},
		{
			"length": 16,
			"notes": [
				{
					"strumTime": 56000,
					"sustain": 0,
					"direction": 2,
					"noteAnim": "singUP",
					"noteType": "",
					"mustPress": true
				},
				{
					"strumTime": 56333.3359,
					"sustain": 0,
					"direction": 0,
					"noteAnim": "singLEFT",
					"noteType": "",
					"mustPress": true
				},
				{
					"strumTime": 56666.668,
					"sustain": 0,
					"direction": 2,
					"noteAnim": "singUP",
					"noteType": "",
					"mustPress": true
				},
				{
					"strumTime": 57000,
					"sustain": 0,
					"direction": 0,
					"noteAnim": "singLEFT",
					"noteType": "",
					"mustPress": true
				},
				{
					"strumTime": 57166.668,
					"sustain": 0,
					"direction": 3,
					"noteAnim": "singRIGHT",
					"noteType": "",
					"mustPress": true
				}
			]
		},
		{
			"length": 16,
			"notes": [
				{
					"strumTime": 57333.3359,
					"sustain": 0,
					"direction": 2,
					"noteAnim": "singUP",
					"noteType": "",
					"mustPress": true
				},
				{
					"strumTime": 57500,
					"sustain": 0,
					"direction": 3,
					"noteAnim": "singRIGHT",
					"noteType": "",
					"mustPress": true
				},
				{
					"strumTime": 57666.668,
					"sustain": 0,
					"direction": 0,
					"noteAnim": "singLEFT",
					"noteType": "",
					"mustPress": true
				},
				{
					"strumTime": 58000,
					"sustain": 0,
					"direction": 2,
					"noteAnim": "singUP",
					"noteType": "",
					"mustPress": true
				},
				{
					"strumTime": 58333.3359,
					"sustain": 0,
					"direction": 0,
					"noteAnim": "singLEFT",
					"noteType": "",
					"mustPress": true
				},
				{
					"strumTime": 58500,
					"sustain": 0,
					"direction": 3,
					"noteAnim": "singRIGHT",
					"noteType": "",
					"mustPress": true
				}
			]
		},
		{
			"length": 16,
			"notes": [
				{
					"strumTime": 58666.668,
					"sustain": 0,
					"direction": 1,
					"noteAnim": "singDOWN",
					"noteType": "",
					"mustPress": false
				},
				{
					"strumTime": 59000,
					"sustain": 0,
					"direction": 0,
					"noteAnim": "singLEFT",
					"noteType": "",
					"mustPress": false
				},
				{
					"strumTime": 59166.668,
					"sustain": 0,
					"direction": 3,
					"noteAnim": "singRIGHT",
					"noteType": "",
					"mustPress": false
				},
				{
					"strumTime": 59333.3359,
					"sustain": 0,
					"direction": 1,
					"noteAnim": "singDOWN",
					"noteType": "",
					"mustPress": false
				},
				{
					"strumTime": 59666.668,
					"sustain": 0,
					"direction": 1,
					"noteAnim": "singDOWN",
					"noteType": "",
					"mustPress": false
				}
			]
		},
		{
			"length": 16,
			"notes": [
				{
					"strumTime": 60000,
					"sustain": 0,
					"direction": 1,
					"noteAnim": "singDOWN",
					"noteType": "",
					"mustPress": false
				},
				{
					"strumTime": 60333.3359,
					"sustain": 0,
					"direction": 0,
					"noteAnim": "singLEFT",
					"noteType": "",
					"mustPress": false
				},
				{
					"strumTime": 60500,
					"sustain": 0,
					"direction": 0,
					"noteAnim": "singLEFT",
					"noteType": "",
					"mustPress": false
				},
				{
					"strumTime": 60666.668,
					"sustain": 0,
					"direction": 3,
					"noteAnim": "singRIGHT",
					"noteType": "",
					"mustPress": false
				},
				{
					"strumTime": 60833.3359,
					"sustain": 0,
					"direction": 3,
					"noteAnim": "singRIGHT",
					"noteType": "",
					"mustPress": false
				},
				{
					"strumTime": 61000,
					"sustain": 0,
					"direction": 3,
					"noteAnim": "singRIGHT",
					"noteType": "",
					"mustPress": false
				},
				{
					"strumTime": 61166.668,
					"sustain": 0,
					"direction": 3,
					"noteAnim": "singRIGHT",
					"noteType": "",
					"mustPress": false
				}
			]
		},
		{
			"length": 16,
			"notes": [
				{
					"strumTime": 61333.3359,
					"sustain": 0,
					"direction": 1,
					"noteAnim": "singDOWN",
					"noteType": "",
					"mustPress": true
				},
				{
					"strumTime": 61666.668,
					"sustain": 0,
					"direction": 0,
					"noteAnim": "singLEFT",
					"noteType": "",
					"mustPress": true
				},
				{
					"strumTime": 61833.3359,
					"sustain": 0,
					"direction": 3,
					"noteAnim": "singRIGHT",
					"noteType": "",
					"mustPress": true
				},
				{
					"strumTime": 62000,
					"sustain": 0,
					"direction": 1,
					"noteAnim": "singDOWN",
					"noteType": "",
					"mustPress": true
				},
				{
					"strumTime": 62333.3359,
					"sustain": 0,
					"direction": 1,
					"noteAnim": "singDOWN",
					"noteType": "",
					"mustPress": true
				}
			]
		},
		{
			"length": 16,
			"notes": [
				{
					"strumTime": 62666.668,
					"sustain": 0,
					"direction": 0,
					"noteAnim": "singLEFT",
					"noteType": "",
					"mustPress": false
				},
				{
					"strumTime": 62666.668,
					"sustain": 0,
					"direction": 1,
					"noteAnim": "singDOWN",
					"noteType": "",
					"mustPress": true
				},
				{
					"strumTime": 62833.3359,
					"sustain": 0,
					"direction": 1,
					"noteAnim": "singDOWN",
					"noteType": "",
					"mustPress": false
				},
				{
					"strumTime": 63000,
					"sustain": 0,
					"direction": 3,
					"noteAnim": "singRIGHT",
					"noteType": "",
					"mustPress": false
				},
				{
					"strumTime": 63000,
					"sustain": 0,
					"direction": 0,
					"noteAnim": "singLEFT",
					"noteType": "",
					"mustPress": true
				},
				{
					"strumTime": 63166.668,
					"sustain": 0,
					"direction": 1,
					"noteAnim": "singDOWN",
					"noteType": "",
					"mustPress": false
				},
				{
					"strumTime": 63166.668,
					"sustain": 0,
					"direction": 0,
					"noteAnim": "singLEFT",
					"noteType": "",
					"mustPress": true
				},
				{
					"strumTime": 63333.3359,
					"sustain": 0,
					"direction": 0,
					"noteAnim": "singLEFT",
					"noteType": "",
					"mustPress": false
				},
				{
					"strumTime": 63333.3359,
					"sustain": 0,
					"direction": 3,
					"noteAnim": "singRIGHT",
					"noteType": "",
					"mustPress": true
				},
				{
					"strumTime": 63500,
					"sustain": 0,
					"direction": 1,
					"noteAnim": "singDOWN",
					"noteType": "",
					"mustPress": false
				},
				{
					"strumTime": 63500,
					"sustain": 0,
					"direction": 3,
					"noteAnim": "singRIGHT",
					"noteType": "",
					"mustPress": true
				},
				{
					"strumTime": 63666.668,
					"sustain": 0,
					"direction": 3,
					"noteAnim": "singRIGHT",
					"noteType": "",
					"mustPress": false
				},
				{
					"strumTime": 63666.668,
					"sustain": 0,
					"direction": 3,
					"noteAnim": "singRIGHT",
					"noteType": "",
					"mustPress": true
				},
				{
					"strumTime": 63833.3359,
					"sustain": 333.333344,
					"direction": 1,
					"noteAnim": "singDOWN",
					"noteType": "",
					"mustPress": false
				},
				{
					"strumTime": 63833.3359,
					"sustain": 0,
					"direction": 3,
					"noteAnim": "singRIGHT",
					"noteType": "",
					"mustPress": true
				}
			]
		},
		{
			"length": 16,
			"notes": [
				{
					"strumTime": 64333.3359,
					"sustain": 0,
					"direction": 2,
					"noteAnim": "singUP",
					"noteType": "",
					"mustPress": false
				},
				{
					"strumTime": 64500.0039,
					"sustain": 0,
					"direction": 1,
					"noteAnim": "singDOWN",
					"noteType": "",
					"mustPress": false
				},
				{
					"strumTime": 64666.668,
					"sustain": 0,
					"direction": 3,
					"noteAnim": "singRIGHT",
					"noteType": "",
					"mustPress": false
				}
			]
		},
		{
			"length": 16,
			"notes": [
				{
					"strumTime": 65500.0039,
					"sustain": 0,
					"direction": 1,
					"noteAnim": "singDOWN",
					"noteType": "",
					"mustPress": false
				},
				{
					"strumTime": 65666.67,
					"sustain": 0,
					"direction": 3,
					"noteAnim": "singRIGHT",
					"noteType": "",
					"mustPress": false
				},
				{
					"strumTime": 66000,
					"sustain": 0,
					"direction": 0,
					"noteAnim": "singLEFT",
					"noteType": "",
					"mustPress": false
				}
			]
		},
		{
			"length": 16,
			"notes": [
				{
					"strumTime": 67000,
					"sustain": 0,
					"direction": 2,
					"noteAnim": "singUP",
					"noteType": "",
					"mustPress": false
				},
				{
					"strumTime": 67333.3359,
					"sustain": 0,
					"direction": 1,
					"noteAnim": "singDOWN",
					"noteType": "",
					"mustPress": false
				},
				{
					"strumTime": 67666.67,
					"sustain": 0,
					"direction": 0,
					"noteAnim": "singLEFT",
					"noteType": "",
					"mustPress": false
				},
				{
					"strumTime": 67833.3359,
					"sustain": 0,
					"direction": 1,
					"noteAnim": "singDOWN",
					"noteType": "",
					"mustPress": false
				}
			]
		},
		{
			"length": 16,
			"notes": [
				{
					"strumTime": 68000,
					"sustain": 0,
					"direction": 0,
					"noteAnim": "singLEFT",
					"noteType": "",
					"mustPress": true
				},
				{
					"strumTime": 68000,
					"sustain": 0,
					"direction": 2,
					"noteAnim": "singUP",
					"noteType": "",
					"mustPress": false
				},
				{
					"strumTime": 68166.67,
					"sustain": 0,
					"direction": 1,
					"noteAnim": "singDOWN",
					"noteType": "",
					"mustPress": true
				},
				{
					"strumTime": 68166.67,
					"sustain": 0,
					"direction": 3,
					"noteAnim": "singRIGHT",
					"noteType": "",
					"mustPress": false
				},
				{
					"strumTime": 68333.3359,
					"sustain": 0,
					"direction": 3,
					"noteAnim": "singRIGHT",
					"noteType": "",
					"mustPress": true
				},
				{
					"strumTime": 68333.3359,
					"sustain": 0,
					"direction": 0,
					"noteAnim": "singLEFT",
					"noteType": "",
					"mustPress": false
				},
				{
					"strumTime": 68500,
					"sustain": 0,
					"direction": 1,
					"noteAnim": "singDOWN",
					"noteType": "",
					"mustPress": true
				},
				{
					"strumTime": 68500,
					"sustain": 0,
					"direction": 3,
					"noteAnim": "singRIGHT",
					"noteType": "",
					"mustPress": false
				},
				{
					"strumTime": 68666.67,
					"sustain": 0,
					"direction": 0,
					"noteAnim": "singLEFT",
					"noteType": "",
					"mustPress": true
				},
				{
					"strumTime": 68666.67,
					"sustain": 0,
					"direction": 2,
					"noteAnim": "singUP",
					"noteType": "",
					"mustPress": false
				},
				{
					"strumTime": 68833.3359,
					"sustain": 0,
					"direction": 1,
					"noteAnim": "singDOWN",
					"noteType": "",
					"mustPress": true
				},
				{
					"strumTime": 69000,
					"sustain": 0,
					"direction": 3,
					"noteAnim": "singRIGHT",
					"noteType": "",
					"mustPress": true
				},
				{
					"strumTime": 69166.67,
					"sustain": 333.333344,
					"direction": 1,
					"noteAnim": "singDOWN",
					"noteType": "",
					"mustPress": true
				}
			]
		},
		{
			"length": 16,
			"notes": [
				{
					"strumTime": 69666.67,
					"sustain": 0,
					"direction": 2,
					"noteAnim": "singUP",
					"noteType": "",
					"mustPress": true
				},
				{
					"strumTime": 69833.3359,
					"sustain": 0,
					"direction": 1,
					"noteAnim": "singDOWN",
					"noteType": "",
					"mustPress": true
				},
				{
					"strumTime": 70000,
					"sustain": 0,
					"direction": 3,
					"noteAnim": "singRIGHT",
					"noteType": "",
					"mustPress": true
				}
			]
		},
		{
			"length": 16,
			"notes": [
				{
					"strumTime": 70833.3359,
					"sustain": 0,
					"direction": 1,
					"noteAnim": "singDOWN",
					"noteType": "",
					"mustPress": true
				},
				{
					"strumTime": 71000,
					"sustain": 0,
					"direction": 3,
					"noteAnim": "singRIGHT",
					"noteType": "",
					"mustPress": true
				},
				{
					"strumTime": 71333.3359,
					"sustain": 0,
					"direction": 0,
					"noteAnim": "singLEFT",
					"noteType": "",
					"mustPress": true
				}
			]
		},
		{
			"length": 16,
			"notes": [
				{
					"strumTime": 72333.3359,
					"sustain": 0,
					"direction": 2,
					"noteAnim": "singUP",
					"noteType": "",
					"mustPress": true
				},
				{
					"strumTime": 72666.67,
					"sustain": 0,
					"direction": 1,
					"noteAnim": "singDOWN",
					"noteType": "",
					"mustPress": true
				},
				{
					"strumTime": 73000,
					"sustain": 0,
					"direction": 0,
					"noteAnim": "singLEFT",
					"noteType": "",
					"mustPress": true
				},
				{
					"strumTime": 73166.67,
					"sustain": 0,
					"direction": 1,
					"noteAnim": "singDOWN",
					"noteType": "",
					"mustPress": true
				}
			]
		},
		{
			"length": 16,
			"notes": [
				{
					"strumTime": 73333.3359,
					"sustain": 0,
					"direction": 2,
					"noteAnim": "singUP",
					"noteType": "",
					"mustPress": true
				},
				{
					"strumTime": 73500,
					"sustain": 0,
					"direction": 3,
					"noteAnim": "singRIGHT",
					"noteType": "",
					"mustPress": true
				},
				{
					"strumTime": 73666.67,
					"sustain": 0,
					"direction": 0,
					"noteAnim": "singLEFT",
					"noteType": "",
					"mustPress": true
				},
				{
					"strumTime": 73833.3359,
					"sustain": 0,
					"direction": 3,
					"noteAnim": "singRIGHT",
					"noteType": "",
					"mustPress": true
				},
				{
					"strumTime": 74000,
					"sustain": 0,
					"direction": 2,
					"noteAnim": "singUP",
					"noteType": "",
					"mustPress": true
				}
			]
		},
		{
			"length": 16,
			"notes": [
				{
					"strumTime": 74666.67,
					"sustain": 0,
					"direction": 2,
					"noteAnim": "singUP",
					"noteType": "",
					"mustPress": false
				},
				{
					"strumTime": 75000,
					"sustain": 0,
					"direction": 0,
					"noteAnim": "singLEFT",
					"noteType": "",
					"mustPress": false
				},
				{
					"strumTime": 75333.3359,
					"sustain": 0,
					"direction": 2,
					"noteAnim": "singUP",
					"noteType": "",
					"mustPress": false
				},
				{
					"strumTime": 75666.67,
					"sustain": 0,
					"direction": 0,
					"noteAnim": "singLEFT",
					"noteType": "",
					"mustPress": false
				},
				{
					"strumTime": 75833.3359,
					"sustain": 0,
					"direction": 3,
					"noteAnim": "singRIGHT",
					"noteType": "",
					"mustPress": false
				}
			]
		},
		{
			"length": 16,
			"notes": [
				{
					"strumTime": 76000,
					"sustain": 0,
					"direction": 2,
					"noteAnim": "singUP",
					"noteType": "",
					"mustPress": false
				},
				{
					"strumTime": 76166.67,
					"sustain": 0,
					"direction": 3,
					"noteAnim": "singRIGHT",
					"noteType": "",
					"mustPress": false
				},
				{
					"strumTime": 76333.3359,
					"sustain": 0,
					"direction": 0,
					"noteAnim": "singLEFT",
					"noteType": "",
					"mustPress": false
				},
				{
					"strumTime": 76666.67,
					"sustain": 0,
					"direction": 2,
					"noteAnim": "singUP",
					"noteType": "",
					"mustPress": false
				},
				{
					"strumTime": 77000,
					"sustain": 0,
					"direction": 2,
					"noteAnim": "singUP",
					"noteType": "",
					"mustPress": false
				}
			]
		},
		{
			"length": 16,
			"notes": [
				{
					"strumTime": 77333.3359,
					"sustain": 0,
					"direction": 2,
					"noteAnim": "singUP",
					"noteType": "",
					"mustPress": true
				},
				{
					"strumTime": 77666.67,
					"sustain": 0,
					"direction": 0,
					"noteAnim": "singLEFT",
					"noteType": "",
					"mustPress": true
				},
				{
					"strumTime": 78000,
					"sustain": 0,
					"direction": 2,
					"noteAnim": "singUP",
					"noteType": "",
					"mustPress": true
				},
				{
					"strumTime": 78333.3359,
					"sustain": 0,
					"direction": 0,
					"noteAnim": "singLEFT",
					"noteType": "",
					"mustPress": true
				},
				{
					"strumTime": 78500,
					"sustain": 0,
					"direction": 3,
					"noteAnim": "singRIGHT",
					"noteType": "",
					"mustPress": true
				}
			]
		},
		{
			"length": 16,
			"notes": [
				{
					"strumTime": 78666.67,
					"sustain": 0,
					"direction": 2,
					"noteAnim": "singUP",
					"noteType": "",
					"mustPress": true
				},
				{
					"strumTime": 78833.3359,
					"sustain": 0,
					"direction": 3,
					"noteAnim": "singRIGHT",
					"noteType": "",
					"mustPress": true
				},
				{
					"strumTime": 79000,
					"sustain": 0,
					"direction": 0,
					"noteAnim": "singLEFT",
					"noteType": "",
					"mustPress": true
				},
				{
					"strumTime": 79333.3359,
					"sustain": 0,
					"direction": 2,
					"noteAnim": "singUP",
					"noteType": "",
					"mustPress": true
				},
				{
					"strumTime": 79666.67,
					"sustain": 0,
					"direction": 2,
					"noteAnim": "singUP",
					"noteType": "",
					"mustPress": true
				}
			]
		},
		{
			"length": 16,
			"notes": [
				{
					"strumTime": 80000,
					"sustain": 0,
					"direction": 1,
					"noteAnim": "singDOWN",
					"noteType": "",
					"mustPress": false
				},
				{
					"strumTime": 80333.3359,
					"sustain": 0,
					"direction": 0,
					"noteAnim": "singLEFT",
					"noteType": "",
					"mustPress": false
				},
				{
					"strumTime": 80500,
					"sustain": 0,
					"direction": 3,
					"noteAnim": "singRIGHT",
					"noteType": "",
					"mustPress": false
				},
				{
					"strumTime": 80666.67,
					"sustain": 0,
					"direction": 1,
					"noteAnim": "singDOWN",
					"noteType": "",
					"mustPress": false
				}
			]
		},
		{
			"length": 16,
			"notes": [
				{
					"strumTime": 81333.3359,
					"sustain": 0,
					"direction": 1,
					"noteAnim": "singDOWN",
					"noteType": "",
					"mustPress": false
				},
				{
					"strumTime": 81666.67,
					"sustain": 0,
					"direction": 1,
					"noteAnim": "singDOWN",
					"noteType": "",
					"mustPress": false
				},
				{
					"strumTime": 82000,
					"sustain": 0,
					"direction": 1,
					"noteAnim": "singDOWN",
					"noteType": "",
					"mustPress": false
				}
			]
		},
		{
			"length": 16,
			"notes": [
				{
					"strumTime": 82666.67,
					"sustain": 0,
					"direction": 1,
					"noteAnim": "singDOWN",
					"noteType": "",
					"mustPress": true
				},
				{
					"strumTime": 83000,
					"sustain": 0,
					"direction": 0,
					"noteAnim": "singLEFT",
					"noteType": "",
					"mustPress": true
				},
				{
					"strumTime": 83166.67,
					"sustain": 0,
					"direction": 3,
					"noteAnim": "singRIGHT",
					"noteType": "",
					"mustPress": true
				},
				{
					"strumTime": 83333.3359,
					"sustain": 0,
					"direction": 1,
					"noteAnim": "singDOWN",
					"noteType": "",
					"mustPress": true
				}
			]
		},
		{
			"length": 16,
			"notes": [
				{
					"strumTime": 84000,
					"sustain": 0,
					"direction": 1,
					"noteAnim": "singDOWN",
					"noteType": "",
					"mustPress": true
				},
				{
					"strumTime": 84333.3359,
					"sustain": 0,
					"direction": 1,
					"noteAnim": "singDOWN",
					"noteType": "",
					"mustPress": true
				},
				{
					"strumTime": 84666.67,
					"sustain": 0,
					"direction": 1,
					"noteAnim": "singDOWN",
					"noteType": "",
					"mustPress": true
				}
			]
		},
		{
			"length": 16,
			"notes": []
		}
	],
	"song": "Dadbattle",
	"bpmMapping": [],
	"extraData": {}
}